Workbook

Sheet README
A1: Alphabet (GOOGL) — DCF & multiples valuation model
A3: Purpose: teaching demo (Demo 3, 'Agentic AI: Define-Design-Build'). Not investment advice.
A4: Units: $ millions unless stated; per-share values in $. Valuation date and price on 'Assumptions'.
A6: Colour legend
A7: Blue text = hardcoded input you can change · Black = formula · Green = link to another sheet · Yellow fill = key assumption
A9: Sheets
A10: Assumptions — market data, WACC inputs, terminal value inputs, and 2026–2030 drivers by segment
A11: Historicals — FY2023–FY2025 actuals, H1 2026 and Q2 2026 (sourced)
A12: Projections — segment revenue, EBIT, NOPAT, D&A, capex and unlevered free cash flow, 2026E–2030E
A13: DCF — WACC build, stub-period discounting (mid-year), terminal value, equity value per share
A14: Sensitivity — price per share across WACC × terminal growth (live formulas)
A15: Multiples — peer P/E, EV/Sales, EV/EBITDA (MSFT, META, AMZN) and implied GOOGL value
... A30: • Risk-free rate and ERP are analyst inputs — update to current market levels before use.

Sheet Assumptions
A1: Assumptions & drivers
A2: Edit blue cells. Yellow = key assumptions.
A3: Market data
A4: Valuation date | B4: 46311 | C4: Model date
A5: Share price ($) | B5: 340.59 | C5: GOOGL close, 16 Oct 2026 (StockAnalysis.com)
A6: Shares outstanding (mm) | B6: 12230 | C6: Class A+B+C at 30 Jun 2026 (Q2 2026 8-K)
A7: Cash & marketable securities ($mm) | B7: 242474 | C7: 30 Jun 2026 (Q2 2026 8-K)
A8: Long-term debt ($mm) | B8: 98165 | C8: 30 Jun 2026 (Q2 2026 8-K); excludes lease liabilities
A10: WACC inputs
A11: Risk-free rate | B11: 0.042 | C11: Analyst input — approx. 10-yr US Treasury; update before use
A12: Equity beta (5-yr) | B12: 1.21 | C12: StockAnalysis.com, 16 Oct 2026
A13: Equity risk premium | B13: 0.045 | C13: Analyst input
A14: Pre-tax cost of debt | B14: 0.048 | C14: Analyst input (high-grade corporate yield)
A15: Tax rate | B15: 0.165 | C15: FY2025 effective rate 16.8% (26,656 / 158,826)
A17: Terminal value
A18: Terminal growth (g) | B18: 0.03 | C18: Analyst input
A19: Terminal capex ÷ D&A | B19: 1.1 | C19: Steady-state reinvestment: capex normalises to 1.1× depreciation after the AI build-out
A20: Stub: fraction of 2026 remaining | B20: =(DATE(2026,12,31)-B4)/365 -> 0.20821918 | C20: Only this share of 2026E FCF is counted
A22: Driver | B22: 2026E | C22: 2027E | D22: 2028E | E22: 2029E | F22: 2030E | H22: Rationale
A23: Search & other — growth | B23: 0.14 | C23: 0.11 | D23: 0.09 | E23: 0.08 | F23: 0.07 | H23: Q2 2026 +16.8% YoY (63,271 vs 54,190); decelerates
A24: YouTube ads — growth | B24: 0.12 | C24: 0.11 | D24: 0.1 | E24: 0.09 | F24: 0.08 | H24: Q2 2026 +12.9% YoY
A25: Google Network — growth | B25: -0.02 | C25: -0.02 | D25: -0.02 | E25: -0.02 | F25: -0.02 | H25: Q2 2026 −0.7% YoY; secular decline
A26: Subscriptions, platforms & devices — growth | B26: 0.15 | C26: 0.13 | D26: 0.12 | E26: 0.11 | F26: 0.1 | H26: Q2 2026 +15.2% YoY
A27: Google Cloud — growth | B27: 0.68 | C27: 0.45 | D27: 0.33 | E27: 0.25 | F27: 0.2 | H27: Q2 2026 +82% YoY; backlog $514B, ~half recognised within 24 months
A28: Other Bets — growth | B28: 0.1 | C28: 0.1 | D28: 0.1 | E28: 0.1 | F28: 0.1 | H28: Small; Q2 2026 +2.4%
A29: EBIT margin | B29: 0.34 | C29: 0.325 | D29: 0.335 | E29: 0.35 | F29: 0.36 | H29: H1 2026 35.0% (80,466 / 229,692); depreciation from AI capex weighs in 2027
A30: D&A % of revenue | B30: 0.08 | C30: 0.11 | D30: 0.13 | E30: 0.14 | F30: 0.145 | H30: FY2025 5.2%; rises as $195–205B 2026 capex is depreciated
A31: Capex % of revenue | B31: 0.41 | C31: 0.46 | D31: 0.38 | E31: 0.32 | F31: 0.26 | H31: 2026 ≈ $200B = guidance midpoint ($195–205B); 2027 'significantly' higher; then normalises
A32: Change in NWC % of change in revenue | B32: 0.02 | C32: 0.02 | D32: 0.02 | E32: 0.02 | F32: 0.02 | H32: Low working-capital needs

Sheet Summary
A1: Valuation summary — Alphabet (GOOGL), $ per share
A3: Method | B3: Low | C3: Base / median | D3: High | E3: vs. price (base)
A4: DCF (WACC 9–10%, g 2.5–3.5%) | B4: =Sensitivity!C9 -> 198.75217 | C4: =DCF!B38 -> 230.27324 | D4: =Sensitivity!E7 -> 274.788 | E4: =C4/$B$9-1 -> -0.32389901
A5: EV / Sales — peers | B5: =Multiples!B23 -> 144.50334 | C5: =Multiples!C23 -> 302.36246 | D5: =Multiples!D23 -> 450.74275 | E5: =C5/$B$9-1 -> -0.11223917
A6: EV / EBITDA — peers | B6: =Multiples!B24 -> 246.54962 | C6: =Multiples!C24 -> 248.67341 | D6: =Multiples!D24 -> 303.04253 | E6: =C6/$B$9-1 -> -0.2698746
A7: Forward P/E — peers | B7: =Multiples!B25 -> 307.02384 | C7: =Multiples!C25 -> 354.04311 | D7: =Multiples!D25 -> 356.30749 | E7: =C7/$B$9-1 -> 0.039499413
A9: Current share price | B9: =Assumptions!B5 -> 340.59
A10: Blended base (average of 4 methods) | B10: =AVERAGE(C4:C7) -> 283.83805
A11: Blended vs. price | B11: =B10/B9-1 -> -0.16662834
A13: DCF low = WACC 10.0% & g 2.5%; high = WACC 9.0% & g 3.5% (Sensitivity grid), around the ~9.5% base WACC. Multiples: low/median/high peer multiple.

Sheet Historicals
A1: Historical financials ($mm)
A2: Blue = reported figures. FY2025 revenue by type = sum of Q1–Q4 2025 releases.
A3: Line item | B3: FY2023 | C3: FY2024 | D3: FY2025 | E3: H1 2026 | F3: Q2 2026
A4: Google Search & other | B4: 175033 | C4: 198084 | D4: 224532 | F4: 63271
A5: YouTube ads | B5: 31510 | C5: 36147 | D5: 40367 | F5: 11055
A6: Google Network | B6: 31312 | C6: 30359 | D6: 29792 | F6: 7303
A7: Subscriptions, platforms & devices | B7: 34688 | C7: 40340 | D7: 48030 | F7: 12911
A8: Google Cloud | B8: 33088 | C8: 43229 | D8: 58705 | F8: 24768
A9: Other Bets | B9: 1527 | C9: 1648 | D9: 1537 | F9: 382
A10: Hedging gains (losses) | B10: 236 | C10: 211 | D10: -127 | F10: 106
A11: Total revenues | B11: =SUM(B4:B10) -> 307394 | C11: =SUM(C4:C10) -> 350018 | D11: =SUM(D4:D10) -> 402836 | E11: 229692 | F11: =SUM(F4:F10) -> 119796
A12: Revenue growth | C12: =C11/B11-1 -> 0.13866243 | D12: =D11/C11-1 -> 0.15090081
A13: Cost of revenues | B13: 133332 | C13: 146306 | D13: 162535
A14: Research & development | B14: 45427 | C14: 49326 | D14: 61087
A15: Sales & marketing | B15: 27917 | C15: 27808 | D15: 28693
A16: General & administrative | B16: 16425 | C16: 14188 | D16: 21482
A17: Operating income | B17: =B11-SUM(B13:B16) -> 84293 | C17: =C11-SUM(C13:C16) -> 112390 | D17: =D11-SUM(D13:D16) -> 129039 | E17: 80466 | F17: 40770
A18: Operating margin | B18: =B17/B11 -> 0.2742181 | C18: =C17/C11 -> 0.32109777 | D18: =D17/D11 -> 0.32032639 | E18: =E17/E11 -> 0.3503213 | F18: =F17/F11 -> 0.34032856
A19: Check: reported operating income | B19: 84293 | C19: 112390 | D19: 129039
A20: Other income (expense), net | B20: 1424 | C20: 7425 | D20: 29787
A21: Income before taxes | B21: =B17+B20 -> 85717 | C21: =C17+C20 -> 119815 | D21: =D17+D20 -> 158826
A22: Provision for income taxes | B22: 11922 | C22: 19697 | D22: 26656
A23: Net income | B23: =B21-B22 -> 73795 | C23: =C21-C22 -> 100118 | D23: =D21-D22 -> 132170 | E23: 174771 | F23: 112193 | G23: H1/Q2 2026 include a $99.0B gain on equity securities in Q2
A24: Effective tax rate | B24: =B22/B21 -> 0.1390856 | C24: =C22/C21 -> 0.16439511 | D24: =D22/D21 -> 0.16783146
A25: Diluted EPS ($) | B25: 5.8 | C25: 8.04 | D25: 10.81 | E25: 14.24 | F25: 9.11
A27: Cash flow
A28: Depreciation of property & equipment | B28: 11946 | C28: 15311 | D28: 21136
A29: Stock-based compensation | B29: 22460 | C29: 22785 | D29: 24953
A30: Net cash from operating activities | B30: 101746 | C30: 125299 | D30: 164713 | E30: 84859 | F30: 39069
A31: Purchases of property & equipment (capex) | B31: 32251 | C31: 52535 | D31: 91447 | E31: 80598 | F31: 44924
A32: Free cash flow (OCF − capex) | B32: =B30-B31 -> 69495 | C32: =C30-C31 -> 72764 | D32: =D30-D31 -> 73266 | E32: =E30-E31 -> 4261 | F32: =F30-F31 -> -5855
A33: Capex % of revenue | B33: =B31/B11 -> 0.10491747 | C33: =C31/C11 -> 0.15009228 | D33: =D31/D11 -> 0.22700801 | E33: =E31/E11 -> 0.35089598 | F33: =F31/F11 -> 0.37500417
A34: D&A % of revenue | B34: =B28/B11 -> 0.038862177 | C34: =C28/C11 -> 0.043743465 | D34: =D28/D11 -> 0.052468002
A36: Balance sheet (period end)
A37: Cash, equivalents & marketable securities | B37: 110916 | C37: 95657 | D37: 126843 | E37: 242474
A38: Long-term debt | B38: 13253 | C38: 10883 | D38: 46547 | E38: 98165
A39: Shares outstanding (mm) | C39: 12211 | D39: 12088 | E39: 12230
A41: Sources: FY2024–FY2025 from Q4 2025 release (8-K Ex. 99.1); FY2023 from FY2023 10-K; H1/Q2 2026 from Q2 2026 release (8-K, 22 Jul 2026). Q2 2026 hedging = total less segments.

Sheet Projections
A1: Projections ($mm)
A2: Formulas only — change drivers on 'Assumptions'.
A3: Line item | B3: FY2025A | C3: 2026E | D3: 2027E | E3: 2028E | F3: 2029E | G3: 2030E
A4: Google Search & other | B4: =Historicals!D4 -> 224532 | C4: =B4*(1+Assumptions!B23) -> 255966.48 | D4: =C4*(1+Assumptions!C23) -> 284122.79 | E4: =D4*(1+Assumptions!D23) -> 309693.84 | F4: =E4*(1+Assumptions!E23) -> 334469.35 | G4: =F4*(1+Assumptions!F23) -> 357882.21
A5: YouTube ads | B5: =Historicals!D5 -> 40367 | C5: =B5*(1+Assumptions!B24) -> 45211.04 | D5: =C5*(1+Assumptions!C24) -> 50184.254 | E5: =D5*(1+Assumptions!D24) -> 55202.68 | F5: =E5*(1+Assumptions!E24) -> 60170.921 | G5: =F5*(1+Assumptions!F24) -> 64984.595
A6: Google Network | B6: =Historicals!D6 -> 29792 | C6: =B6*(1+Assumptions!B25) -> 29196.16 | D6: =C6*(1+Assumptions!C25) -> 28612.237 | E6: =D6*(1+Assumptions!D25) -> 28039.992 | F6: =E6*(1+Assumptions!E25) -> 27479.192 | G6: =F6*(1+Assumptions!F25) -> 26929.608
A7: Subscriptions, platforms & devices | B7: =Historicals!D7 -> 48030 | C7: =B7*(1+Assumptions!B26) -> 55234.5 | D7: =C7*(1+Assumptions!C26) -> 62414.985 | E7: =D7*(1+Assumptions!D26) -> 69904.783 | F7: =E7*(1+Assumptions!E26) -> 77594.309 | G7: =F7*(1+Assumptions!F26) -> 85353.74
A8: Google Cloud | B8: =Historicals!D8 -> 58705 | C8: =B8*(1+Assumptions!B27) -> 98624.4 | D8: =C8*(1+Assumptions!C27) -> 143005.38 | E8: =D8*(1+Assumptions!D27) -> 190197.16 | F8: =E8*(1+Assumptions!E27) -> 237746.44 | G8: =F8*(1+Assumptions!F27) -> 285295.73
A9: Other Bets | B9: =Historicals!D9 -> 1537 | C9: =B9*(1+Assumptions!B28) -> 1690.7 | D9: =C9*(1+Assumptions!C28) -> 1859.77 | E9: =D9*(1+Assumptions!D28) -> 2045.747 | F9: =E9*(1+Assumptions!E28) -> 2250.3217 | G9: =F9*(1+Assumptions!F28) -> 2475.3539
A10: Hedging gains (losses) | B10: =Historicals!D10 -> -127 | C10: 0 | D10: 0 | E10: 0 | F10: 0 | G10: 0
A11: Total revenues | B11: =SUM(B4:B10) -> 402836 | C11: =SUM(C4:C10) -> 485923.28 | D11: =SUM(D4:D10) -> 570199.42 | E11: =SUM(E4:E10) -> 655084.2 | F11: =SUM(F4:F10) -> 739710.54 | G11: =SUM(G4:G10) -> 822921.24
A12: Growth | C12: =C11/B11-1 -> 0.20625585 | D12: =D11/C11-1 -> 0.17343507 | E12: =E11/D11-1 -> 0.14886859 | F12: =F11/E11-1 -> 0.12918391 | G12: =G11/F11-1 -> 0.11249089
A13: Cloud share of revenue | B13: =B8/B11 -> 0.14572928 | C13: =C8/C11 -> 0.2029629 | D13: =D8/D11 -> 0.25079889 | E13: =E8/E11 -> 0.29034001 | F13: =F8/F11 -> 0.3214047 | G13: =G8/G11 -> 0.34668656
A15: EBIT | B15: =Historicals!D17 -> 129039 | C15: =C11*Assumptions!B29 -> 165213.92 | D15: =D11*Assumptions!C29 -> 185314.81 | E15: =E11*Assumptions!D29 -> 219453.21 | F15: =F11*Assumptions!E29 -> 258898.69 | G15: =G11*Assumptions!F29 -> 296251.65
A16: EBIT margin | B16: =B15/B11 -> 0.32032639 | C16: =C15/C11 -> 0.34 | D16: =D15/D11 -> 0.325 | E16: =E15/E11 -> 0.335 | F16: =F15/F11 -> 0.35 | G16: =G15/G11 -> 0.36
A17: Taxes on EBIT | C17: =-C15*Assumptions!$B$15 -> -27260.296 | D17: =-D15*Assumptions!$B$15 -> -30576.944 | E17: =-E15*Assumptions!$B$15 -> -36209.779 | F17: =-F15*Assumptions!$B$15 -> -42718.284 | G17: =-G15*Assumptions!$B$15 -> -48881.521
A18: NOPAT | C18: =C15+C17 -> 137953.62 | D18: =D15+D17 -> 154737.87 | E18: =E15+E17 -> 183243.43 | F18: =F15+F17 -> 216180.41 | G18: =G15+G17 -> 247370.12
A19: Plus: D&A | B19: =Historicals!D28 -> 21136 | C19: =C11*Assumptions!B30 -> 38873.862 | D19: =D11*Assumptions!C30 -> 62721.936 | E19: =E11*Assumptions!D30 -> 85160.946 | F19: =F11*Assumptions!E30 -> 103559.48 | G19: =G11*Assumptions!F30 -> 119323.58
A20: Less: capex | B20: =-Historicals!D31 -> -91447 | C20: =-C11*Assumptions!B31 -> -199228.54 | D20: =-D11*Assumptions!C31 -> -262291.73 | E20: =-E11*Assumptions!D31 -> -248932 | F20: =-F11*Assumptions!E31 -> -236707.37 | G20: =-G11*Assumptions!F31 -> -213959.52
A21: Less: increase in NWC | C21: =-(C11-B11)*Assumptions!B32 -> -1661.7456 | D21: =-(D11-C11)*Assumptions!C32 -> -1685.5228 | E21: =-(E11-D11)*Assumptions!D32 -> -1697.6957 | F21: =-(F11-E11)*Assumptions!E32 -> -1692.5268 | G21: =-(G11-F11)*Assumptions!F32 -> -1664.2139
A22: Unlevered free cash flow | C22: =C18+C19+C20+C21 -> -24062.809 | D22: =D18+D19+D20+D21 -> -46517.452 | E22: =E18+E19+E20+E21 -> 17774.682 | F22: =F18+F19+F20+F21 -> 81339.981 | G22: =G18+G19+G20+G21 -> 151069.97
A24: Memo: capex ($B) vs. 2026 guidance $195–205B | C24: =-C20/1000 -> 199.22854 | D24: =-D20/1000 -> 262.29173 | E24: =-E20/1000 -> 248.932 | F24: =-F20/1000 -> 236.70737 | G24: =-G20/1000 -> 213.95952
A25: Memo: operating EPS (NOPAT ÷ shares, $) | C25: =C18/Assumptions!$B$6 -> 11.279936 | D25: =D18/Assumptions!$B$6 -> 12.652319 | E25: =E18/Assumptions!$B$6 -> 14.983109 | F25: =F18/Assumptions!$B$6 -> 17.676239 | G25: =G18/Assumptions!$B$6 -> 20.226502

Sheet DCF
A1: Discounted cash flow
A3: WACC
A4: Cost of equity (CAPM) | B4: =Assumptions!B11+Assumptions!B12*Assumptions!B13 -> 0.09645
A5: After-tax cost of debt | B5: =Assumptions!B14*(1-Assumptions!B15) -> 0.04008
A6: Market value of equity ($mm) | B6: =Assumptions!B5*Assumptions!B6 -> 4165415.7
A7: Debt ($mm) | B7: =Assumptions!B8 -> 98165
A8: Equity weight | B8: =B6/(B6+B7) -> 0.97697593
A9: Debt weight | B9: =B7/(B6+B7) -> 0.023024075
A10: WACC | B10: =B8*B4+B9*B5 -> 0.095152133
A12: Discounting | B12: 2026E | C12: 2027E | D12: 2028E | E12: 2029E | F12: 2030E
A13: Unlevered FCF ($mm) | B13: =Projections!C22 -> -24062.809 | C13: =Projections!D22 -> -46517.452 | D13: =Projections!E22 -> 17774.682 | E13: =Projections!F22 -> 81339.981 | F13: =Projections!G22 -> 151069.97
A14: Share of year counted | B14: =Assumptions!B20 -> 0.20821918 | C14: 1 | D14: 1 | E14: 1 | F14: 1
A15: FCF counted ($mm) | B15: =B13*B14 -> -5010.3383 | C15: =C13*C14 -> -46517.452 | D15: =D13*D14 -> 17774.682 | E15: =E13*E14 -> 81339.981 | F15: =F13*F14 -> 151069.97
A16: Discount period (years, mid-period) | B16: =B14/2 -> 0.10410959 | C16: =$B$14+0.5 -> 0.70821918 | D16: =C16+1 -> 1.7082192 | E16: =D16+1 -> 2.7082192 | F16: =E16+1 -> 3.7082192
A17: Discount factor | B17: =1/(1+$B$10)^B16 -> 0.99058177 | C17: =1/(1+$B$10)^C16 -> 0.93765578 | D17: =1/(1+$B$10)^D16 -> 0.85618769 | E17: =1/(1+$B$10)^E16 -> 0.78179795 | F17: =1/(1+$B$10)^F16 -> 0.71387155
A18: Present value ($mm) | B18: =B15*B17 -> -4963.1497 | C18: =C15*C17 -> -43617.358 | D18: =D15*D17 -> 15218.464 | E18: =E15*E17 -> 63591.431 | F18: =F15*F17 -> 107844.55
A20: Terminal value
A21: Terminal-year NOPAT (2030 × (1+g)) | B21: =Projections!G18*(1+Assumptions!B18) -> 254791.23
A22: Terminal-year D&A | B22: =Projections!G19*(1+Assumptions!B18) -> 122903.29
A23: Terminal capex (D&A × ratio) | B23: =-B22*Assumptions!B19 -> -135193.62
A24: Terminal increase in NWC | B24: =-Projections!G11*Assumptions!B18*Assumptions!F32 -> -493.75274
A25: Terminal FCF | B25: =SUM(B21:B24) -> 242007.15
A26: Terminal value at end-2030 (Gordon growth) | B26: =B25/(B10-Assumptions!B18) -> 3714493.1
A27: Years to end-2030 | B27: =Assumptions!B20+4 -> 4.2082192
A28: PV of terminal value | B28: =B26/(1+B10)^B27 -> 2533858.7
A30: Valuation
A31: Sum of PV of FCF (2026 stub–2030) | B31: =SUM(B18:F18) -> 138073.94
A32: PV of terminal value | B32: =B28 -> 2533858.7
A33: Enterprise value | B33: =B31+B32 -> 2671932.7
A34: Plus: cash & marketable securities | B34: =Assumptions!B7 -> 242474
A35: Less: debt | B35: =-Assumptions!B8 -> -98165
A36: Equity value | B36: =SUM(B33:B35) -> 2816241.7
A37: Shares outstanding (mm) | B37: =Assumptions!B6 -> 12230
A38: Implied value per share ($) | B38: =B36/B37 -> 230.27324
A39: Current share price ($) | B39: =Assumptions!B5 -> 340.59
A40: Upside / (downside) | B40: =B38/B39-1 -> -0.32389901
A41: Terminal value % of EV | B41: =B32/B33 -> 0.94832432
A42: Implied EV / 2027E EBITDA | B42: =B33/(Projections!D15+Projections!D19) -> 10.772326
A44: Read-across: if implied value is below the price, the market is pricing faster Cloud growth, higher terminal margins or lower long-run capex than the base case — test them on 'Sensitivity'.

Sheet Sensitivity
A1: Implied value per share ($): WACC × terminal growth
A2: Each cell recomputes the full DCF with live formulas. Base case highlighted.
A4: WACC ↓ / g → | B4: 0.02 | C4: 0.025 | D4: 0.03 | E4: 0.035 | F4: 0.04
A5: 0.08 | B5: =(SUMPRODUCT(DCF!$B$15:$F$15/(1+$A5)^DCF!$B$16:$F$16)+(Projections!$G$18*(1+B$4)+Projections!$G$19*(1+B$4)*(1-Assumptions!$B$19)-Projections!$G$11*B$4*Assumptions!$F$32)/($A5-B$4)/(1+$A5)^DCF!$B$27+Assumptions!$B$7-Assumptions!$B$8)/Assumptions!$B$6 -> 260.15138 | C5: =(SUMPRODUCT(DCF!$B$15:$F$15/(1+$A5)^DCF!$B$16:$F$16)+(Projections!$G$18*(1+C$4)+Projections!$G$19*(1+C$4)*(1-Assumptions!$B$19)-Projections!$G$11*C$4*Assumptions!$F$32)/($A5-C$4)/(1+$A5)^DCF!$B$27+Assumptions!$B$7-Assumptions!$B$8)/Assumptions!$B$6 -> 282.81975 | D5: =(SUMPRODUCT(DCF!$B$15:$F$15/(1+$A5)^DCF!$B$16:$F$16)+(Projections!$G$18*(1+D$4)+Projections!$G$19*(1+D$4)*(1-Assumptions!$B$19)-Projections!$G$11*D$4*Assumptions!$F$32)/($A5-D$4)/(1+$A5)^DCF!$B$27+Assumptions!$B$7-Assumptions!$B$8)/Assumptions!$B$6 -> 310.02179 | E5: =(SUMPRODUCT(DCF!$B$15:$F$15/(1+$A5)^DCF!$B$16:$F$16)+(Projections!$G$18*(1+E$4)+Projections!$G$19*(1+E$4)*(1-Assumptions!$B$19)-Projections!$G$11*E$4*Assumptions!$F$32)/($A5-E$4)/(1+$A5)^DCF!$B$27+Assumptions!$B$7-Assumptions!$B$8)/Assumptions!$B$6 -> 343.26873 | F5: =(SUMPRODUCT(DCF!$B$15:$F$15/(1+$A5)^DCF!$B$16:$F$16)+(Projections!$G$18*(1+F$4)+Projections!$G$19*(1+F$4)*(1-Assumptions!$B$19)-Projections!$G$11*F$4*Assumptions!$F$32)/($A5-F$4)/(1+$A5)^DCF!$B$27+Assumptions!$B$7-Assumptions!$B$8)/Assumptions!$B$6 -> 384.82741
A6: 0.085 | B6: =(SUMPRODUCT(DCF!$B$15:$F$15/(1+$A6)^DCF!$B$16:$F$16)+(Projections!$G$18*(1+B$4)+Projections!$G$19*(1+B$4)*(1-Assumptions!$B$19)-Projections!$G$11*B$4*Assumptions!$F$32)/($A6-B$4)/(1+$A6)^DCF!$B$27+Assumptions!$B$7-Assumptions!$B$8)/Assumptions!$B$6 -> 237.54323 | C6: =(SUMPRODUCT(DCF!$B$15:$F$15/(1+$A6)^DCF!$B$16:$F$16)+(Projections!$G$18*(1+C$4)+Projections!$G$19*(1+C$4)*(1-Assumptions!$B$19)-Projections!$G$11*C$4*Assumptions!$F$32)/($A6-C$4)/(1+$A6)^DCF!$B$27+Assumptions!$B$7-Assumptions!$B$8)/Assumptions!$B$6 -> 256.43635 | D6: =(SUMPRODUCT(DCF!$B$15:$F$15/(1+$A6)^DCF!$B$16:$F$16)+(Projections!$G$18*(1+D$4)+Projections!$G$19*(1+D$4)*(1-Assumptions!$B$19)-Projections!$G$11*D$4*Assumptions!$F$32)/($A6-D$4)/(1+$A6)^DCF!$B$27+Assumptions!$B$7-Assumptions!$B$8)/Assumptions!$B$6 -> 278.76459 | E6: =(SUMPRODUCT(DCF!$B$15:$F$15/(1+$A6)^DCF!$B$16:$F$16)+(Projections!$G$18*(1+E$4)+Projections!$G$19*(1+E$4)*(1-Assumptions!$B$19)-Projections!$G$11*E$4*Assumptions!$F$32)/($A6-E$4)/(1+$A6)^DCF!$B$27+Assumptions!$B$7-Assumptions!$B$8)/Assumptions!$B$6 -> 305.55848 | F6: =(SUMPRODUCT(DCF!$B$15:$F$15/(1+$A6)^DCF!$B$16:$F$16)+(Projections!$G$18*(1+F$4)+Projections!$G$19*(1+F$4)*(1-Assumptions!$B$19)-Projections!$G$11*F$4*Assumptions!$F$32)/($A6-F$4)/(1+$A6)^DCF!$B$27+Assumptions!$B$7-Assumptions!$B$8)/Assumptions!$B$6 -> 338.30656
A7: 0.09 | B7: =(SUMPRODUCT(DCF!$B$15:$F$15/(1+$A7)^DCF!$B$16:$F$16)+(Projections!$G$18*(1+B$4)+Projections!$G$19*(1+B$4)*(1-Assumptions!$B$19)-Projections!$G$11*B$4*Assumptions!$F$32)/($A7-B$4)/(1+$A7)^DCF!$B$27+Assumptions!$B$7-Assumptions!$B$8)/Assumptions!$B$6 -> 218.23004 | C7: =(SUMPRODUCT(DCF!$B$15:$F$15/(1+$A7)^DCF!$B$16:$F$16)+(Projections!$G$18*(1+C$4)+Projections!$G$19*(1+C$4)*(1-Assumptions!$B$19)-Projections!$G$11*C$4*Assumptions!$F$32)/($A7-C$4)/(1+$A7)^DCF!$B$27+Assumptions!$B$7-Assumptions!$B$8)/Assumptions!$B$6 -> 234.18229 | D7: =(SUMPRODUCT(DCF!$B$15:$F$15/(1+$A7)^DCF!$B$16:$F$16)+(Projections!$G$18*(1+D$4)+Projections!$G$19*(1+D$4)*(1-Assumptions!$B$19)-Projections!$G$11*D$4*Assumptions!$F$32)/($A7-D$4)/(1+$A7)^DCF!$B$27+Assumptions!$B$7-Assumptions!$B$8)/Assumptions!$B$6 -> 252.79324 | E7: =(SUMPRODUCT(DCF!$B$15:$F$15/(1+$A7)^DCF!$B$16:$F$16)+(Projections!$G$18*(1+E$4)+Projections!$G$19*(1+E$4)*(1-Assumptions!$B$19)-Projections!$G$11*E$4*Assumptions!$F$32)/($A7-E$4)/(1+$A7)^DCF!$B$27+Assumptions!$B$7-Assumptions!$B$8)/Assumptions!$B$6 -> 274.788 | F7: =(SUMPRODUCT(DCF!$B$15:$F$15/(1+$A7)^DCF!$B$16:$F$16)+(Projections!$G$18*(1+F$4)+Projections!$G$19*(1+F$4)*(1-Assumptions!$B$19)-Projections!$G$11*F$4*Assumptions!$F$32)/($A7-F$4)/(1+$A7)^DCF!$B$27+Assumptions!$B$7-Assumptions!$B$8)/Assumptions!$B$6 -> 301.18172
A8: 0.095 | B8: =(SUMPRODUCT(DCF!$B$15:$F$15/(1+$A8)^DCF!$B$16:$F$16)+(Projections!$G$18*(1+B$4)+Projections!$G$19*(1+B$4)*(1-Assumptions!$B$19)-Projections!$G$11*B$4*Assumptions!$F$32)/($A8-B$4)/(1+$A8)^DCF!$B$27+Assumptions!$B$7-Assumptions!$B$8)/Assumptions!$B$6 -> 201.55118 | C8: =(SUMPRODUCT(DCF!$B$15:$F$15/(1+$A8)^DCF!$B$16:$F$16)+(Projections!$G$18*(1+C$4)+Projections!$G$19*(1+C$4)*(1-Assumptions!$B$19)-Projections!$G$11*C$4*Assumptions!$F$32)/($A8-C$4)/(1+$A8)^DCF!$B$27+Assumptions!$B$7-Assumptions!$B$8)/Assumptions!$B$6 -> 215.17093 | D8: =(SUMPRODUCT(DCF!$B$15:$F$15/(1+$A8)^DCF!$B$16:$F$16)+(Projections!$G$18*(1+D$4)+Projections!$G$19*(1+D$4)*(1-Assumptions!$B$19)-Projections!$G$11*D$4*Assumptions!$F$32)/($A8-D$4)/(1+$A8)^DCF!$B$27+Assumptions!$B$7-Assumptions!$B$8)/Assumptions!$B$6 -> 230.88603 | E8: =(SUMPRODUCT(DCF!$B$15:$F$15/(1+$A8)^DCF!$B$16:$F$16)+(Projections!$G$18*(1+E$4)+Projections!$G$19*(1+E$4)*(1-Assumptions!$B$19)-Projections!$G$11*E$4*Assumptions!$F$32)/($A8-E$4)/(1+$A8)^DCF!$B$27+Assumptions!$B$7-Assumptions!$B$8)/Assumptions!$B$6 -> 249.22032 | F8: =(SUMPRODUCT(DCF!$B$15:$F$15/(1+$A8)^DCF!$B$16:$F$16)+(Projections!$G$18*(1+F$4)+Projections!$G$19*(1+F$4)*(1-Assumptions!$B$19)-Projections!$G$11*F$4*Assumptions!$F$32)/($A8-F$4)/(1+$A8)^DCF!$B$27+Assumptions!$B$7-Assumptions!$B$8)/Assumptions!$B$6 -> 270.88811
A9: 0.1 | B9: =(SUMPRODUCT(DCF!$B$15:$F$15/(1+$A9)^DCF!$B$16:$F$16)+(Projections!$G$18*(1+B$4)+Projections!$G$19*(1+B$4)*(1-Assumptions!$B$19)-Projections!$G$11*B$4*Assumptions!$F$32)/($A9-B$4)/(1+$A9)^DCF!$B$27+Assumptions!$B$7-Assumptions!$B$8)/Assumptions!$B$6 -> 187.01123 | C9: =(SUMPRODUCT(DCF!$B$15:$F$15/(1+$A9)^DCF!$B$16:$F$16)+(Projections!$G$18*(1+C$4)+Projections!$G$19*(1+C$4)*(1-Assumptions!$B$19)-Projections!$G$11*C$4*Assumptions!$F$32)/($A9-C$4)/(1+$A9)^DCF!$B$27+Assumptions!$B$7-Assumptions!$B$8)/Assumptions!$B$6 -> 198.75217 | D9: =(SUMPRODUCT(DCF!$B$15:$F$15/(1+$A9)^DCF!$B$16:$F$16)+(Projections!$G$18*(1+D$4)+Projections!$G$19*(1+D$4)*(1-Assumptions!$B$19)-Projections!$G$11*D$4*Assumptions!$F$32)/($A9-D$4)/(1+$A9)^DCF!$B$27+Assumptions!$B$7-Assumptions!$B$8)/Assumptions!$B$6 -> 212.17039 | E9: =(SUMPRODUCT(DCF!$B$15:$F$15/(1+$A9)^DCF!$B$16:$F$16)+(Projections!$G$18*(1+E$4)+Projections!$G$19*(1+E$4)*(1-Assumptions!$B$19)-Projections!$G$11*E$4*Assumptions!$F$32)/($A9-E$4)/(1+$A9)^DCF!$B$27+Assumptions!$B$7-Assumptions!$B$8)/Assumptions!$B$6 -> 227.65294 | F9: =(SUMPRODUCT(DCF!$B$15:$F$15/(1+$A9)^DCF!$B$16:$F$16)+(Projections!$G$18*(1+F$4)+Projections!$G$19*(1+F$4)*(1-Assumptions!$B$19)-Projections!$G$11*F$4*Assumptions!$F$32)/($A9-F$4)/(1+$A9)^DCF!$B$27+Assumptions!$B$7-Assumptions!$B$8)/Assumptions!$B$6 -> 245.71593
A10: 0.105 | B10: =(SUMPRODUCT(DCF!$B$15:$F$15/(1+$A10)^DCF!$B$16:$F$16)+(Projections!$G$18*(1+B$4)+Projections!$G$19*(1+B$4)*(1-Assumptions!$B$19)-Projections!$G$11*B$4*Assumptions!$F$32)/($A10-B$4)/(1+$A10)^DCF!$B$27+Assumptions!$B$7-Assumptions!$B$8)/Assumptions!$B$6 -> 174.23139 | C10: =(SUMPRODUCT(DCF!$B$15:$F$15/(1+$A10)^DCF!$B$16:$F$16)+(Projections!$G$18*(1+C$4)+Projections!$G$19*(1+C$4)*(1-Assumptions!$B$19)-Projections!$G$11*C$4*Assumptions!$F$32)/($A10-C$4)/(1+$A10)^DCF!$B$27+Assumptions!$B$7-Assumptions!$B$8)/Assumptions!$B$6 -> 184.43845 | D10: =(SUMPRODUCT(DCF!$B$15:$F$15/(1+$A10)^DCF!$B$16:$F$16)+(Projections!$G$18*(1+D$4)+Projections!$G$19*(1+D$4)*(1-Assumptions!$B$19)-Projections!$G$11*D$4*Assumptions!$F$32)/($A10-D$4)/(1+$A10)^DCF!$B$27+Assumptions!$B$7-Assumptions!$B$8)/Assumptions!$B$6 -> 196.00645 | E10: =(SUMPRODUCT(DCF!$B$15:$F$15/(1+$A10)^DCF!$B$16:$F$16)+(Projections!$G$18*(1+E$4)+Projections!$G$19*(1+E$4)*(1-Assumptions!$B$19)-Projections!$G$11*E$4*Assumptions!$F$32)/($A10-E$4)/(1+$A10)^DCF!$B$27+Assumptions!$B$7-Assumptions!$B$8)/Assumptions!$B$6 -> 209.22702 | F10: =(SUMPRODUCT(DCF!$B$15:$F$15/(1+$A10)^DCF!$B$16:$F$16)+(Projections!$G$18*(1+F$4)+Projections!$G$19*(1+F$4)*(1-Assumptions!$B$19)-Projections!$G$11*F$4*Assumptions!$F$32)/($A10-F$4)/(1+$A10)^DCF!$B$27+Assumptions!$B$7-Assumptions!$B$8)/Assumptions!$B$6 -> 224.48153
A11: 0.11 | B11: =(SUMPRODUCT(DCF!$B$15:$F$15/(1+$A11)^DCF!$B$16:$F$16)+(Projections!$G$18*(1+B$4)+Projections!$G$19*(1+B$4)*(1-Assumptions!$B$19)-Projections!$G$11*B$4*Assumptions!$F$32)/($A11-B$4)/(1+$A11)^DCF!$B$27+Assumptions!$B$7-Assumptions!$B$8)/Assumptions!$B$6 -> 162.91708 | C11: =(SUMPRODUCT(DCF!$B$15:$F$15/(1+$A11)^DCF!$B$16:$F$16)+(Projections!$G$18*(1+C$4)+Projections!$G$19*(1+C$4)*(1-Assumptions!$B$19)-Projections!$G$11*C$4*Assumptions!$F$32)/($A11-C$4)/(1+$A11)^DCF!$B$27+Assumptions!$B$7-Assumptions!$B$8)/Assumptions!$B$6 -> 171.85699 | D11: =(SUMPRODUCT(DCF!$B$15:$F$15/(1+$A11)^DCF!$B$16:$F$16)+(Projections!$G$18*(1+D$4)+Projections!$G$19*(1+D$4)*(1-Assumptions!$B$19)-Projections!$G$11*D$4*Assumptions!$F$32)/($A11-D$4)/(1+$A11)^DCF!$B$27+Assumptions!$B$7-Assumptions!$B$8)/Assumptions!$B$6 -> 181.91438 | E11: =(SUMPRODUCT(DCF!$B$15:$F$15/(1+$A11)^DCF!$B$16:$F$16)+(Projections!$G$18*(1+E$4)+Projections!$G$19*(1+E$4)*(1-Assumptions!$B$19)-Projections!$G$11*E$4*Assumptions!$F$32)/($A11-E$4)/(1+$A11)^DCF!$B$27+Assumptions!$B$7-Assumptions!$B$8)/Assumptions!$B$6 -> 193.31277 | F11: =(SUMPRODUCT(DCF!$B$15:$F$15/(1+$A11)^DCF!$B$16:$F$16)+(Projections!$G$18*(1+F$4)+Projections!$G$19*(1+F$4)*(1-Assumptions!$B$19)-Projections!$G$11*F$4*Assumptions!$F$32)/($A11-F$4)/(1+$A11)^DCF!$B$27+Assumptions!$B$7-Assumptions!$B$8)/Assumptions!$B$6 -> 206.33949
A13: Current price | B13: =Assumptions!B5 -> 340.59
A14: Base-case WACC | B14: =DCF!B10 -> 0.095152133

Sheet Multiples
A1: Trading multiples — peers (close 16 Oct 2026)
A2: Source: StockAnalysis.com statistics pages (S&P Global Market Intelligence data). Blue = input.
A4: Company | B4: Price ($) | C4: Market cap ($B) | D4: EV ($B) | E4: P/E (TTM) | F4: Forward P/E | G4: EV/Sales (TTM) | H4: EV/EBITDA (TTM) | I4: Revenue TTM ($B)
A5: Microsoft (MSFT) | B5: 529.05 | C5: 3930 | D5: 3980 | E5: 29.47 | F5: 26.75 | G5: 12.04 | H5: 20.57 | I5: 331.84
A6: Meta Platforms (META) | B6: 709.33 | C6: 1810 | D6: 1830 | E6: 27.76 | F6: 23.05 | G6: 7.97 | H6: 16.58 | I6: 228.25
A7: Amazon.com (AMZN) | B7: 250 | C7: 2700 | D7: 2830 | E7: 20.1 | F7: 26.58 | G7: 3.64 | H7: 16.73 | I7: 775.68
A8: Peer median | E8: =MEDIAN(E5:E7) -> 27.76 | F8: =MEDIAN(F5:F7) -> 26.58 | G8: =MEDIAN(G5:G7) -> 7.97 | H8: =MEDIAN(H5:H7) -> 16.73
A9: Peer low | E9: =MIN(E5:E7) -> 20.1 | F9: =MIN(F5:F7) -> 23.05 | G9: =MIN(G5:G7) -> 3.64 | H9: =MIN(H5:H7) -> 16.58
A10: Peer high | E10: =MAX(E5:E7) -> 29.47 | F10: =MAX(F5:F7) -> 26.75 | G10: =MAX(G5:G7) -> 12.04 | H10: =MAX(H5:H7) -> 20.57
A12: Alphabet (GOOGL) | B12: 340.59 | C12: 4170 | D12: 4040 | E12: 17.09 | F12: 25.57 | G12: 9.14 | H12: 23.52 | I12: 445.87
A13: GOOGL TTM P/E is depressed by the $99B Q2 2026 equity-securities gain — use forward P/E.
A15: GOOGL inputs
A16: TTM revenue ($mm) | B16: =I12*1000 -> 445870
A17: TTM EBITDA ($mm) | B17: 173160 | C17: StockAnalysis.com, TTM to 30 Jun 2026
A18: Forward EPS ($) = price ÷ forward P/E | B18: =B12/F12 -> 13.319906
A19: Net cash ($mm) | B19: =Assumptions!B7-Assumptions!B8 -> 144309
A20: Shares (mm) | B20: =Assumptions!B6 -> 12230
A22: Implied value per share ($) | B22: Low | C22: Median | D22: High
A23: EV / Sales (TTM) | B23: =($B$16*G9+$B$19)/$B$20 -> 144.50334 | C23: =($B$16*G8+$B$19)/$B$20 -> 302.36246 | D23: =($B$16*G10+$B$19)/$B$20 -> 450.74275
A24: EV / EBITDA (TTM) | B24: =($B$17*H9+$B$19)/$B$20 -> 246.54962 | C24: =($B$17*H8+$B$19)/$B$20 -> 248.67341 | D24: =($B$17*H10+$B$19)/$B$20 -> 303.04253
A25: Forward P/E | B25: =$B$18*F9 -> 307.02384 | C25: =$B$18*F8 -> 354.04311 | D25: =$B$18*F10 -> 356.30749
