Workbook

Sheet README
C2: Alphabet valuation teaching model
C4: Case selected | D4: =CHOOSE(Assumptions!$D$4,"Base","Bull","Bear") -> Base
C6: USD millions, except per-share values. Financials through June 30, 2026; valuation October 17, 2026.
C8: Prices are October 16 closes from Google Finance. Exchange-direct verification was unavailable.
C10: Blue = sourced numeric input. Yellow = editable key driver. Black = formula. Green = cross-sheet formula.
C12: One forecast build responds to the Base / Bull / Bear selector in Assumptions!D4.
C14: Low / active / high DCF values are discount-rate and growth bounds for the selected operating case.
C16: SBC stays in EBIT and is never added back. D&A and capex are modeled separately.
C18: The stub uses the remaining share of projected H2 cash flow; annual flows use mid-year discounting.
C20: Terminal capex is normalized to D&A × the editable ratio. This dominates value and is not guidance.
C22: Search, YouTube, Network and subscriptions EBIT margins are allocations, not disclosed segment profits.
C24: Cash bridge uses June 30 balances with no July–October roll-forward. Equity stakes are treated explicitly.
C26: Preferred stock is deducted at liquidation preference; conversion and capped calls are not option-priced.
C28: Non-marketable investments are excluded in Base. Deferred tax and accrued legal claims are deducted.
... C104: https://data.sec.gov/api/xbrl/companyfacts/CIK0001018724.json

Sheet Assumptions
C2: Assumptions
C4: Case selected | D4: 1 | F4: =CHOOSE(D4,"Base","Bull","Bear") -> Base | J4: 1 Base / 2 Bull / 3 Bear. Change only this selector.
C6: Valuation date | D6: 46312 | J6: User requested date, America/Los_Angeles
C7: GOOGL closing price | D7: 340.59 | J7: Q1: October 16, 2026 close. Vendor quote, not exchange-direct.
C8: Quote date | D8: 46311 | J8: Q1: last trading close before valuation date
C9: Risk-free rate assumption | D9: 0.045 | J9: A1: rounded teaching assumption, not a verified current Treasury yield.
C10: Beta assumption | D10: 1.2 | J10: A1: teaching beta, not a regression estimate.
C11: Equity risk premium assumption | D11: 0.045 | J11: A1: teaching ERP, not a market fact.
C12: Pre-tax cost of debt proxy | D12: 0.048 | J12: S2 Note 6: Q1 USD issue weighted coupon 4.80%; current yield may differ.
C13: Normalized tax rate | D13: 0.2 | J13: A1: operating tax assumption; H1 GAAP tax includes investment gains.
C14: Terminal growth | D14: 0.03 | J14: A1: perpetual nominal growth, independent of forecast growth.
C15: Terminal capex / D&A | D15: 1.15 | J15: A1: capex exceeds D&A by 15% in steady state; normalized after AI buildout.
C16: Non-marketable stake realization | D16: 0 | J16: A1: exclude unlisted investments; no double count of marketable securities.
C17: 2026 capex guide low | D17: 195000 | J17: S3: July 22, 2026 CFO guidance, USD millions.
C18: 2026 capex guide high | D18: 205000 | J18: S3: July 22, 2026 CFO guidance, USD millions.
C19: 2026 capex guidance midpoint | D19: =AVERAGE(D17:D18) -> 200000
C20: Preferred cost proxy | D20: 0.0625 | J20: S2 Note 11: coupon rate, used as market yield proxy.
C21: WACC sensitivity step | D21: 0.005 | J21: A1: 0.5 percentage point grid interval.
C22: Growth sensitivity step | D22: 0.005 | J22: A1: 0.5 percentage point grid interval.
C23: Forecast hedging gain assumption | D23: 0 | J23: A1: no forecast gains/losses; known H1 actual remains in 2026.
C26: Forecast drivers | D26: 2026E | E26: 2027E | F26: 2028E | G26: 2029E | H26: 2030E | J26: 2026 revenue driver applies to H2 2025 comparable; later years apply to full year.
C28: Search growth — active | D28: =IF(ISNUMBER(CHOOSE($D$4,D29,D30,D31)),CHOOSE($D$4,D29,D30,D31),"Missing input") -> 0.16 | E28: =IF(ISNUMBER(CHOOSE($D$4,E29,E30,E31)),CHOOSE($D$4,E29,E30,E31),"Missing input") -> 0.12 | F28: =IF(ISNUMBER(CHOOSE($D$4,F29,F30,F31)),CHOOSE($D$4,F29,F30,F31),"Missing input") -> 0.1 | G28: =IF(ISNUMBER(CHOOSE($D$4,G29,G30,G31)),CHOOSE($D$4,G29,G30,G31),"Missing input") -> 0.08 | H28: =IF(ISNUMBER(CHOOSE($D$4,H29,H30,H31)),CHOOSE($D$4,H29,H30,H31),"Missing input") -> 0.07 | J28: A1 / S2: H1 Search grew 17.9%; gradual moderation.
C29: Base | D29: 0.16 | E29: 0.12 | F29: 0.1 | G29: 0.08 | H29: 0.07 | J29: A1 / S2: H1 Search grew 17.9%; gradual moderation.
C30: Bull | D30: 0.19 | E30: 0.15 | F30: 0.13 | G30: 0.11 | H30: 0.09 | J30: A1 / S2: H1 Search grew 17.9%; gradual moderation.
C31: Bear | D31: 0.1 | E31: 0.08 | F31: 0.06 | G31: 0.05 | H31: 0.04 | J31: A1 / S2: H1 Search grew 17.9%; gradual moderation.
C33: YouTube growth — active | D33: =IF(ISNUMBER(CHOOSE($D$4,D34,D35,D36)),CHOOSE($D$4,D34,D35,D36),"Missing input") -> 0.13 | E33: =IF(ISNUMBER(CHOOSE($D$4,E34,E35,E36)),CHOOSE($D$4,E34,E35,E36),"Missing input") -> 0.12 | F33: =IF(ISNUMBER(CHOOSE($D$4,F34,F35,F36)),CHOOSE($D$4,F34,F35,F36),"Missing input") -> 0.11 | G33: =IF(ISNUMBER(CHOOSE($D$4,G34,G35,G36)),CHOOSE($D$4,G34,G35,G36),"Missing input") -> 0.1 | H33: =IF(ISNUMBER(CHOOSE($D$4,H34,H35,H36)),CHOOSE($D$4,H34,H35,H36),"Missing input") -> 0.09 | J33: A1 / S2: H1 YouTube grew 11.8%; World Cup timing.
C34: Base | D34: 0.13 | E34: 0.12 | F34: 0.11 | G34: 0.1 | H34: 0.09 | J34: A1 / S2: H1 YouTube grew 11.8%; World Cup timing.
C35: Bull | D35: 0.16 | E35: 0.15 | F35: 0.14 | G35: 0.12 | H35: 0.1 | J35: A1 / S2: H1 YouTube grew 11.8%; World Cup timing.
C36: Bear | D36: 0.08 | E36: 0.07 | F36: 0.06 | G36: 0.05 | H36: 0.05 | J36: A1 / S2: H1 YouTube grew 11.8%; World Cup timing.
C38: Network growth — active | D38: =IF(ISNUMBER(CHOOSE($D$4,D39,D40,D41)),CHOOSE($D$4,D39,D40,D41),"Missing input") -> -0.02 | E38: =IF(ISNUMBER(CHOOSE($D$4,E39,E40,E41)),CHOOSE($D$4,E39,E40,E41),"Missing input") -> -0.02 | F38: =IF(ISNUMBER(CHOOSE($D$4,F39,F40,F41)),CHOOSE($D$4,F39,F40,F41),"Missing input") -> -0.01 | G38: =IF(ISNUMBER(CHOOSE($D$4,G39,G40,G41)),CHOOSE($D$4,G39,G40,G41),"Missing input") -> 0 | H38: =IF(ISNUMBER(CHOOSE($D$4,H39,H40,H41)),CHOOSE($D$4,H39,H40,H41),"Missing input") -> 0 | J38: A1 / S2: H1 Network contracted 2.3%.
C39: Base | D39: -0.02 | E39: -0.02 | F39: -0.01 | G39: 0 | H39: 0 | J39: A1 / S2: H1 Network contracted 2.3%.
C40: Bull | D40: 0 | E40: 0.01 | F40: 0.01 | G40: 0.01 | H40: 0.01 | J40: A1 / S2: H1 Network contracted 2.3%.
C41: Bear | D41: -0.05 | E41: -0.05 | F41: -0.04 | G41: -0.03 | H41: -0.02 | J41: A1 / S2: H1 Network contracted 2.3%.
C43: Subscriptions & devices growth — active | D43: =IF(ISNUMBER(CHOOSE($D$4,D44,D45,D46)),CHOOSE($D$4,D44,D45,D46),"Missing input") -> 0.16 | E43: =IF(ISNUMBER(CHOOSE($D$4,E44,E45,E46)),CHOOSE($D$4,E44,E45,E46),"Missing input") -> 0.15 | F43: =IF(ISNUMBER(CHOOSE($D$4,F44,F45,F46)),CHOOSE($D$4,F44,F45,F46),"Missing input") -> 0.13 | G43: =IF(ISNUMBER(CHOOSE($D$4,G44,G45,G46)),CHOOSE($D$4,G44,G45,G46),"Missing input") -> 0.12 | H43: =IF(ISNUMBER(CHOOSE($D$4,H44,H45,H46)),CHOOSE($D$4,H44,H45,H46),"Missing input") -> 0.1 | J43: A1 / S2: H1 subscriptions/platforms/devices grew 17.2%.
C44: Base | D44: 0.16 | E44: 0.15 | F44: 0.13 | G44: 0.12 | H44: 0.1 | J44: A1 / S2: H1 subscriptions/platforms/devices grew 17.2%.
C45: Bull | D45: 0.2 | E45: 0.18 | F45: 0.16 | G45: 0.14 | H45: 0.12 | J45: A1 / S2: H1 subscriptions/platforms/devices grew 17.2%.
C46: Bear | D46: 0.1 | E46: 0.09 | F46: 0.08 | G46: 0.07 | H46: 0.06 | J46: A1 / S2: H1 subscriptions/platforms/devices grew 17.2%.
C48: Cloud growth — active | D48: =IF(ISNUMBER(CHOOSE($D$4,D49,D50,D51)),CHOOSE($D$4,D49,D50,D51),"Missing input") -> 0.7 | E48: =IF(ISNUMBER(CHOOSE($D$4,E49,E50,E51)),CHOOSE($D$4,E49,E50,E51),"Missing input") -> 0.5 | F48: =IF(ISNUMBER(CHOOSE($D$4,F49,F50,F51)),CHOOSE($D$4,F49,F50,F51),"Missing input") -> 0.35 | G48: =IF(ISNUMBER(CHOOSE($D$4,G49,G50,G51)),CHOOSE($D$4,G49,G50,G51),"Missing input") -> 0.28 | H48: =IF(ISNUMBER(CHOOSE($D$4,H49,H50,H51)),CHOOSE($D$4,H49,H50,H51),"Missing input") -> 0.22 | J48: A1 / S2 / S3: H1 Cloud +73.1%; $513.9bn backlog, timing uncertain.
C49: Base | D49: 0.7 | E49: 0.5 | F49: 0.35 | G49: 0.28 | H49: 0.22 | J49: A1 / S2 / S3: H1 Cloud +73.1%; $513.9bn backlog, timing uncertain.
C50: Bull | D50: 0.85 | E50: 0.6 | F50: 0.45 | G50: 0.35 | H50: 0.28 | J50: A1 / S2 / S3: H1 Cloud +73.1%; $513.9bn backlog, timing uncertain.
C51: Bear | D51: 0.45 | E51: 0.3 | F51: 0.25 | G51: 0.2 | H51: 0.15 | J51: A1 / S2 / S3: H1 Cloud +73.1%; $513.9bn backlog, timing uncertain.
C53: Other Bets growth — active | D53: =IF(ISNUMBER(CHOOSE($D$4,D54,D55,D56)),CHOOSE($D$4,D54,D55,D56),"Missing input") -> 0.1 | E53: =IF(ISNUMBER(CHOOSE($D$4,E54,E55,E56)),CHOOSE($D$4,E54,E55,E56),"Missing input") -> 0.15 | F53: =IF(ISNUMBER(CHOOSE($D$4,F54,F55,F56)),CHOOSE($D$4,F54,F55,F56),"Missing input") -> 0.15 | G53: =IF(ISNUMBER(CHOOSE($D$4,G54,G55,G56)),CHOOSE($D$4,G54,G55,G56),"Missing input") -> 0.15 | H53: =IF(ISNUMBER(CHOOSE($D$4,H54,H55,H56)),CHOOSE($D$4,H54,H55,H56),"Missing input") -> 0.15 | J53: A1: speculative growth; does not separately value Waymo.
C54: Base | D54: 0.1 | E54: 0.15 | F54: 0.15 | G54: 0.15 | H54: 0.15 | J54: A1: speculative growth; does not separately value Waymo.
C55: Bull | D55: 0.2 | E55: 0.3 | F55: 0.3 | G55: 0.25 | H55: 0.2 | J55: A1: speculative growth; does not separately value Waymo.
C56: Bear | D56: 0 | E56: 0.05 | F56: 0.05 | G56: 0.05 | H56: 0.05 | J56: A1: speculative growth; does not separately value Waymo.
C58: Services EBIT margin — active | D58: =IF(ISNUMBER(CHOOSE($D$4,D59,D60,D61)),CHOOSE($D$4,D59,D60,D61),"Missing input") -> 0.41 | E58: =IF(ISNUMBER(CHOOSE($D$4,E59,E60,E61)),CHOOSE($D$4,E59,E60,E61),"Missing input") -> 0.41 | F58: =IF(ISNUMBER(CHOOSE($D$4,F59,F60,F61)),CHOOSE($D$4,F59,F60,F61),"Missing input") -> 0.42 | G58: =IF(ISNUMBER(CHOOSE($D$4,G59,G60,G61)),CHOOSE($D$4,G59,G60,G61),"Missing input") -> 0.42 | H58: =IF(ISNUMBER(CHOOSE($D$4,H59,H60,H61)),CHOOSE($D$4,H59,H60,H61),"Missing input") -> 0.42 | J58: A1 / S3: Q2 Services margin 41.8%; shared across four revenue categories.
C59: Base | D59: 0.41 | E59: 0.41 | F59: 0.42 | G59: 0.42 | H59: 0.42 | J59: A1 / S3: Q2 Services margin 41.8%; shared across four revenue categories.
C60: Bull | D60: 0.43 | E60: 0.44 | F60: 0.45 | G60: 0.45 | H60: 0.45 | J60: A1 / S3: Q2 Services margin 41.8%; shared across four revenue categories.
C61: Bear | D61: 0.38 | E61: 0.37 | F61: 0.37 | G61: 0.37 | H61: 0.37 | J61: A1 / S3: Q2 Services margin 41.8%; shared across four revenue categories.
C63: Cloud EBIT margin — active | D63: =IF(ISNUMBER(CHOOSE($D$4,D64,D65,D66)),CHOOSE($D$4,D64,D65,D66),"Missing input") -> 0.34 | E63: =IF(ISNUMBER(CHOOSE($D$4,E64,E65,E66)),CHOOSE($D$4,E64,E65,E66),"Missing input") -> 0.33 | F63: =IF(ISNUMBER(CHOOSE($D$4,F64,F65,F66)),CHOOSE($D$4,F64,F65,F66),"Missing input") -> 0.34 | G63: =IF(ISNUMBER(CHOOSE($D$4,G64,G65,G66)),CHOOSE($D$4,G64,G65,G66),"Missing input") -> 0.35 | H63: =IF(ISNUMBER(CHOOSE($D$4,H64,H65,H66)),CHOOSE($D$4,H64,H65,H66),"Missing input") -> 0.36 | J63: A1 / S3: Q2 Cloud margin 35.6%; third-party capacity pressure.
C64: Base | D64: 0.34 | E64: 0.33 | F64: 0.34 | G64: 0.35 | H64: 0.36 | J64: A1 / S3: Q2 Cloud margin 35.6%; third-party capacity pressure.
C65: Bull | D65: 0.36 | E65: 0.37 | F65: 0.38 | G65: 0.39 | H65: 0.4 | J65: A1 / S3: Q2 Cloud margin 35.6%; third-party capacity pressure.
C66: Bear | D66: 0.28 | E66: 0.27 | F66: 0.28 | G66: 0.29 | H66: 0.3 | J66: A1 / S3: Q2 Cloud margin 35.6%; third-party capacity pressure.
C68: Other Bets EBIT margin — active | D68: =IF(ISNUMBER(CHOOSE($D$4,D69,D70,D71)),CHOOSE($D$4,D69,D70,D71),"Missing input") -> -4.5 | E68: =IF(ISNUMBER(CHOOSE($D$4,E69,E70,E71)),CHOOSE($D$4,E69,E70,E71),"Missing input") -> -4 | F68: =IF(ISNUMBER(CHOOSE($D$4,F69,F70,F71)),CHOOSE($D$4,F69,F70,F71),"Missing input") -> -3 | G68: =IF(ISNUMBER(CHOOSE($D$4,G69,G70,G71)),CHOOSE($D$4,G69,G70,G71),"Missing input") -> -2 | H68: =IF(ISNUMBER(CHOOSE($D$4,H69,H70,H71)),CHOOSE($D$4,H69,H70,H71),"Missing input") -> -1 | J68: A1 / S1: substantial losses persist; revenue is small.
C69: Base | D69: -4.5 | E69: -4 | F69: -3 | G69: -2 | H69: -1 | J69: A1 / S1: substantial losses persist; revenue is small.
C70: Bull | D70: -4 | E70: -3 | F70: -2 | G70: -1 | H70: 0 | J70: A1 / S1: substantial losses persist; revenue is small.
C71: Bear | D71: -5 | E71: -5 | F71: -4 | G71: -3 | H71: -2 | J71: A1 / S1: substantial losses persist; revenue is small.
C73: Corporate cost / revenue — active | D73: =IF(ISNUMBER(CHOOSE($D$4,D74,D75,D76)),CHOOSE($D$4,D74,D75,D76),"Missing input") -> 0.05 | E73: =IF(ISNUMBER(CHOOSE($D$4,E74,E75,E76)),CHOOSE($D$4,E74,E75,E76),"Missing input") -> 0.05 | F73: =IF(ISNUMBER(CHOOSE($D$4,F74,F75,F76)),CHOOSE($D$4,F74,F75,F76),"Missing input") -> 0.045 | G73: =IF(ISNUMBER(CHOOSE($D$4,G74,G75,G76)),CHOOSE($D$4,G74,G75,G76),"Missing input") -> 0.04 | H73: =IF(ISNUMBER(CHOOSE($D$4,H74,H75,H76)),CHOOSE($D$4,H74,H75,H76),"Missing input") -> 0.04 | J73: A1 / S3: Q2 Alphabet-level loss $5.8bn, primarily shared AI R&D.
C74: Base | D74: 0.05 | E74: 0.05 | F74: 0.045 | G74: 0.04 | H74: 0.04 | J74: A1 / S3: Q2 Alphabet-level loss $5.8bn, primarily shared AI R&D.
C75: Bull | D75: 0.045 | E75: 0.04 | F75: 0.035 | G75: 0.03 | H75: 0.03 | J75: A1 / S3: Q2 Alphabet-level loss $5.8bn, primarily shared AI R&D.
C76: Bear | D76: 0.06 | E76: 0.06 | F76: 0.06 | G76: 0.055 | H76: 0.05 | J76: A1 / S3: Q2 Alphabet-level loss $5.8bn, primarily shared AI R&D.
C78: D&A / revenue — active | D78: =IF(ISNUMBER(CHOOSE($D$4,D79,D80,D81)),CHOOSE($D$4,D79,D80,D81),"Missing input") -> 0.07 | E78: =IF(ISNUMBER(CHOOSE($D$4,E79,E80,E81)),CHOOSE($D$4,E79,E80,E81),"Missing input") -> 0.1 | F78: =IF(ISNUMBER(CHOOSE($D$4,F79,F80,F81)),CHOOSE($D$4,F79,F80,F81),"Missing input") -> 0.12 | G78: =IF(ISNUMBER(CHOOSE($D$4,G79,G80,G81)),CHOOSE($D$4,G79,G80,G81),"Missing input") -> 0.13 | H78: =IF(ISNUMBER(CHOOSE($D$4,H79,H80,H81)),CHOOSE($D$4,H79,H80,H81),"Missing input") -> 0.13 | J78: A1 / S2: H1 PPE depreciation $13.6bn; forward burden increases.
C79: Base | D79: 0.07 | E79: 0.1 | F79: 0.12 | G79: 0.13 | H79: 0.13 | J79: A1 / S2: H1 PPE depreciation $13.6bn; forward burden increases.
C80: Bull | D80: 0.065 | E80: 0.09 | F80: 0.11 | G80: 0.12 | H80: 0.12 | J80: A1 / S2: H1 PPE depreciation $13.6bn; forward burden increases.
C81: Bear | D81: 0.08 | E81: 0.11 | F81: 0.13 | G81: 0.14 | H81: 0.14 | J81: A1 / S2: H1 PPE depreciation $13.6bn; forward burden increases.
C83: Capex / revenue — active | D83: Guide $200bn | E83: =IF(ISNUMBER(CHOOSE($D$4,E84,E85,E86)),CHOOSE($D$4,E84,E85,E86),"Missing input") -> 0.46 | F83: =IF(ISNUMBER(CHOOSE($D$4,F84,F85,F86)),CHOOSE($D$4,F84,F85,F86),"Missing input") -> 0.36 | G83: =IF(ISNUMBER(CHOOSE($D$4,G84,G85,G86)),CHOOSE($D$4,G84,G85,G86),"Missing input") -> 0.26 | H83: =IF(ISNUMBER(CHOOSE($D$4,H84,H85,H86)),CHOOSE($D$4,H84,H85,H86),"Missing input") -> 0.19 | J83: A1 / S3: 2026 exact $200bn midpoint; 2027+ intensity assumptions.
C84: Base | E84: 0.46 | F84: 0.36 | G84: 0.26 | H84: 0.19 | J84: A1 / S3: 2026 exact $200bn midpoint; 2027+ intensity assumptions.
C85: Bull | E85: 0.4 | F85: 0.3 | G85: 0.22 | H85: 0.16 | J85: A1 / S3: 2026 exact $200bn midpoint; 2027+ intensity assumptions.
C86: Bear | E86: 0.5 | F86: 0.42 | G86: 0.34 | H86: 0.26 | J86: A1 / S3: 2026 exact $200bn midpoint; 2027+ intensity assumptions.
C88: Trade NWC / revenue — active | D88: =IF(ISNUMBER(CHOOSE($D$4,D89,D90,D91)),CHOOSE($D$4,D89,D90,D91),"Missing input") -> 0.1 | E88: =IF(ISNUMBER(CHOOSE($D$4,E89,E90,E91)),CHOOSE($D$4,E89,E90,E91),"Missing input") -> 0.1 | F88: =IF(ISNUMBER(CHOOSE($D$4,F89,F90,F91)),CHOOSE($D$4,F89,F90,F91),"Missing input") -> 0.1 | G88: =IF(ISNUMBER(CHOOSE($D$4,G89,G90,G91)),CHOOSE($D$4,G89,G90,G91),"Missing input") -> 0.1 | H88: =IF(ISNUMBER(CHOOSE($D$4,H89,H90,H91)),CHOOSE($D$4,H89,H90,H91),"Missing input") -> 0.1 | J88: A1 / S2: narrow trade NWC definition; excludes tax and legal balances.
C89: Base | D89: 0.1 | E89: 0.1 | F89: 0.1 | G89: 0.1 | H89: 0.1 | J89: A1 / S2: narrow trade NWC definition; excludes tax and legal balances.
C90: Bull | D90: 0.09 | E90: 0.09 | F90: 0.09 | G90: 0.09 | H90: 0.09 | J90: A1 / S2: narrow trade NWC definition; excludes tax and legal balances.
C91: Bear | D91: 0.12 | E91: 0.12 | F91: 0.12 | G91: 0.12 | H91: 0.12 | J91: A1 / S2: narrow trade NWC definition; excludes tax and legal balances.

Sheet Summary
C2: Summary
C4: Case selected | D4: =CHOOSE(Assumptions!$D$4,"Base","Bull","Bear") -> Base
C6: Valuation date | D6: =Assumptions!D6 -> 46312 | F6: Closing price | G6: =Assumptions!D7 -> 340.59
C8: Value per common share | D8: Low | E8: Active / median | F8: High | G8: Market
C9: DCF | D9: =Sensitivity!E16 -> 158.91956 | E9: =DCF!D51 -> 212.65235 | F9: =Sensitivity!G10 -> 312.30694 | G9: =Assumptions!D7 -> 340.59
C10: P/E (GAAP TTM) | D10: =Multiples!D59 -> 397.75709 | E10: =Multiples!E59 -> 528.72438 | F10: =Multiples!F59 -> 586.40103 | G10: =Assumptions!D7 -> 340.59
C11: EV / Sales | D11: =Multiples!D60 -> 133.90718 | E11: =Multiples!E60 -> 293.83207 | F11: =Multiples!F60 -> 434.43691 | G11: =Assumptions!D7 -> 340.59
C12: EV / EBITD | D12: =Multiples!D61 -> 240.95074 | E12: =Multiples!E61 -> 273.29739 | F12: =Multiples!F61 -> 297.06765 | G12: =Assumptions!D7 -> 340.59
C13: Forward P/E (CY2027 adjusted) | D13: =Multiples!D62 -> 312.36298 | E13: =Multiples!E62 -> 364.83254 | F13: =Multiples!F62 -> 370.9431 | G13: =Assumptions!D7 -> 340.59
C15: Selected-case WACC | D15: =DCF!D15 -> 0.097468734
C16: Terminal growth | D16: =Assumptions!D14 -> 0.03
C17: Terminal value / EV | D17: =DCF!D40 -> 0.9402105
C18: DCF vs closing price | D18: =DCF!D52 -> -0.37563538
C20: 2030 revenue (USD millions) | D20: =Projections!H15 -> 880073.9
C21: 2027 capex intensity | D21: =Assumptions!E83 -> 0.46
C22: 2027 FCF (USD millions) | D22: =Projections!E40 -> -68108.003
C23: Required / modeled terminal FCF | D23: =Sensitivity!D23 -> 1.6609395
C26: DCF bounds: WACC ±1.5 percentage points and growth ±0.5 points, for the selected operating case.
C28: Forward P/E uses CY2027 adjusted consensus, with MSFT calendarized. GAAP P/E includes investment gains.
C30: EV/EBITD = EV / (EBIT + PPE depreciation), using reported inputs. It replaces EBITDA; all intangible amortization remains expensed.

Sheet Historicals
C2: Historicals
C4: Case selected | D4: =CHOOSE(Assumptions!$D$4,"Base","Bull","Bear") -> Base
C6: Reported results | D6: FY2023 | E6: FY2024 | F6: FY2025 | G6: H1 2025 | H6: H1 2026 | J6: S1 annual; S2 interim. USD millions. Interim figures unaudited.
C8: Search & other | D8: 175033 | E8: 198084 | F8: 224532 | G8: 104892 | H8: 123670 | J8: S1 annual; S2 H1. Reported, USD millions except EPS.
C9: YouTube ads | D9: 31510 | E9: 36147 | F9: 40367 | G9: 18723 | H9: 20938 | J9: S1 annual; S2 H1. Reported, USD millions except EPS.
C10: Network | D10: 31312 | E10: 30359 | F10: 29792 | G10: 14610 | H10: 14274 | J10: S1 annual; S2 H1. Reported, USD millions except EPS.
C11: Subscriptions, platforms & devices | D11: 34688 | E11: 40340 | F11: 48030 | G11: 21582 | H11: 25295 | J11: S1 annual; S2 H1. Reported, USD millions except EPS.
C12: Google Cloud | D12: 33088 | E12: 43229 | F12: 58705 | G12: 25884 | H12: 44796 | J12: S1 annual; S2 H1. Reported, USD millions except EPS.
C13: Other Bets | D13: 1527 | E13: 1648 | F13: 1537 | G13: 823 | H13: 793 | J13: S1 annual; S2 H1. Reported, USD millions except EPS.
C14: Hedging gains / (losses) | D14: 236 | E14: 211 | F14: -127 | G14: 148 | H14: -74 | J14: S1 annual; S2 H1. Reported, USD millions except EPS.
C15: Reported revenue | D15: 307394 | E15: 350018 | F15: 402836 | G15: 186662 | H15: 229692 | J15: S1 annual; S2 H1. Reported, USD millions except EPS.
C16: Revenue reconciliation difference | D16: =SUM(D8:D14)-D15 -> 0 | E16: =SUM(E8:E14)-E15 -> 0 | F16: =SUM(F8:F14)-F15 -> 0 | G16: =SUM(G8:G14)-G15 -> 0 | H16: =SUM(H8:H14)-H15 -> 0
C18: Cost of revenue | D18: 133332 | E18: 146306 | F18: 162535 | G18: 75400 | H18: 87214 | J18: S1 annual; S2 H1. Reported, USD millions except EPS.
C19: Research & development | D19: 45427 | E19: 49326 | F19: 61087 | G19: 27364 | H19: 35251 | J19: S1 annual; S2 H1. Reported, USD millions except EPS.
C20: Sales & marketing | D20: 27917 | E20: 27808 | F20: 28693 | G20: 13273 | H20: 16009 | J20: S1 annual; S2 H1. Reported, USD millions except EPS.
C21: General & administrative | D21: 16425 | E21: 14188 | F21: 21482 | G21: 8748 | H21: 10752 | J21: S1 annual; S2 H1. Reported, USD millions except EPS.
C22: Reported operating income | D22: 84293 | E22: 112390 | F22: 129039 | G22: 61877 | H22: 80466 | J22: S1 annual; S2 H1. Reported, USD millions except EPS.
C23: Computed operating income | D23: =D15-SUM(D18:D21) -> 84293 | E23: =E15-SUM(E18:E21) -> 112390 | F23: =F15-SUM(F18:F21) -> 129039 | G23: =G15-SUM(G18:G21) -> 61877 | H23: =H15-SUM(H18:H21) -> 80466
C24: Operating income difference | D24: =D23-D22 -> 0 | E24: =E23-E22 -> 0 | F24: =F23-F22 -> 0 | G24: =G23-G22 -> 0 | H24: =H23-H22 -> 0
C25: Income before tax | D25: 85717 | E25: 119815 | F25: 158826 | G25: 75722 | H25: 216165 | J25: S1 annual; S2 H1. Reported, USD millions except EPS.
C26: Income tax provision | D26: 11922 | E26: 19697 | F26: 26656 | G26: 12986 | H26: 41394 | J26: S1 annual; S2 H1. Reported, USD millions except EPS.
C27: Net income | D27: 73795 | E27: 100118 | F27: 132170 | G27: 62736 | H27: 174771 | J27: S1 annual; S2 H1. Reported, USD millions except EPS.
C28: Net income available to common | D28: 73795 | E28: 100118 | F28: 132170 | G28: 62736 | H28: 174685 | J28: S1 annual; S2 H1. Reported, USD millions except EPS.
C29: Diluted EPS | D29: 5.8 | E29: 8.04 | F29: 10.81 | G29: 5.12 | H29: 14.24 | J29: S1 annual; S2 H1. Reported, USD millions except EPS.
C30: PPE depreciation | D30: 11946 | E30: 15311 | F30: 21136 | G30: 9485 | H30: 13586 | J30: S1 annual; S2 H1. Reported, USD millions except EPS.
C31: Stock-based compensation | D31: 22460 | E31: 22785 | F31: 24953 | G31: 11514 | H31: 14708 | J31: S1 annual; S2 H1. Reported, USD millions except EPS.
C32: Cash from operations | D32: 101746 | E32: 125299 | F32: 164713 | G32: 63897 | H32: 84859 | J32: S1 annual; S2 H1. Reported, USD millions except EPS.
C33: Purchases of PPE (positive outflow) | D33: 32251 | E33: 52535 | F33: 91447 | G33: 39643 | H33: 80598 | J33: S1 annual; S2 H1. Reported, USD millions except EPS.
C34: Computed operating cash flow less capex | D34: =D32-D33 -> 69495 | E34: =E32-E33 -> 72764 | F34: =F32-F33 -> 73266 | G34: =G32-G33 -> 24254 | H34: =H32-H33 -> 4261
C36: Accounts receivable | F36: 62886 | H36: 69175 | J36: S2 balance sheet / notes; point in time. Blank = not collected.
C37: Inventory | F37: 2439 | H37: 9991 | J37: S2 balance sheet / notes; point in time. Blank = not collected.
C38: Accounts payable | F38: 12200 | H38: 20258 | J38: S2 balance sheet / notes; point in time. Blank = not collected.
C39: Deferred revenue, current | F39: 6578 | H39: 7154 | J39: S2 balance sheet / notes; point in time. Blank = not collected.
C40: Computed trade NWC (AR + inventory − AP − deferred revenue) | F40: =SUM(F36:F37)-SUM(F38:F39) -> 46547 | H40: =SUM(H36:H37)-SUM(H38:H39) -> 51754
C42: Cash, equivalents & marketable securities | F42: 126843 | H42: 242474 | J42: S2 balance sheet / notes; point in time. Blank = not collected.
C43: Long-term debt, carrying value | F43: 46547 | H43: 98165 | J43: S2 balance sheet / notes; point in time. Blank = not collected.
C44: Current portion of notes | F44: 1996 | H44: 1999 | J44: S2 balance sheet / notes; point in time. Blank = not collected.
C45: Fair value of notes | F45: 45600 | H45: 94900 | J45: S2 balance sheet / notes; point in time. Blank = not collected.
C46: Other long-term debt, face value | F46: 0 | H46: 1686 | J46: S2 balance sheet / notes; point in time. Blank = not collected.
C47: Common shares outstanding (all classes) | F47: 12088 | H47: 12230 | J47: S2 balance sheet / notes; point in time. Blank = not collected.
C48: Preferred depositary shares, millions | F48: 0 | H48: 385 | J48: S2 balance sheet / notes; point in time. Blank = not collected.
C49: Preference per depositary share, USD | H49: 50 | J49: S2 balance sheet / notes; point in time. Blank = not collected.
C50: Non-marketable securities | F50: 68687 | H50: 131461 | J50: S2 balance sheet / notes; point in time. Blank = not collected.
C51: Deferred income tax liability | F51: 919 | H51: 22819 | J51: S2 balance sheet / notes; point in time. Blank = not collected.
C52: Accrued legal/regulatory claims | H52: 17400 | J52: S2 balance sheet / notes; point in time. Blank = not collected.
C53: H1 intangible amortization | G53: 246 | H53: 545 | J53: S2 balance sheet / notes; point in time. Blank = not collected.
C54: Google Cloud backlog | H54: 513900 | J54: S2 balance sheet / notes; point in time. Blank = not collected.

Sheet Projections
C2: Projections
C4: Case selected | D4: =CHOOSE(Assumptions!$D$4,"Base","Bull","Bear") -> Base
C6: USD millions | D6: 2026E | E6: 2027E | F6: 2028E | G6: 2029E | H6: 2030E
C8: Search & other | D8: =Historicals!H8+(Historicals!F8-Historicals!G8)*(1+Assumptions!D28) -> 262452.4 | E8: =D8*(1+Assumptions!E28) -> 293946.69 | F8: =E8*(1+Assumptions!F28) -> 323341.36 | G8: =F8*(1+Assumptions!G28) -> 349208.67 | H8: =G8*(1+Assumptions!H28) -> 373653.27
C9: YouTube ads | D9: =Historicals!H9+(Historicals!F9-Historicals!G9)*(1+Assumptions!D33) -> 45395.72 | E9: =D9*(1+Assumptions!E33) -> 50843.206 | F9: =E9*(1+Assumptions!F33) -> 56435.959 | G9: =F9*(1+Assumptions!G33) -> 62079.555 | H9: =G9*(1+Assumptions!H33) -> 67666.715
C10: Network | D10: =Historicals!H10+(Historicals!F10-Historicals!G10)*(1+Assumptions!D38) -> 29152.36 | E10: =D10*(1+Assumptions!E38) -> 28569.313 | F10: =E10*(1+Assumptions!F38) -> 28283.62 | G10: =F10*(1+Assumptions!G38) -> 28283.62 | H10: =G10*(1+Assumptions!H38) -> 28283.62
C11: Subscriptions & devices | D11: =Historicals!H11+(Historicals!F11-Historicals!G11)*(1+Assumptions!D43) -> 55974.68 | E11: =D11*(1+Assumptions!E43) -> 64370.882 | F11: =E11*(1+Assumptions!F43) -> 72739.097 | G11: =F11*(1+Assumptions!G43) -> 81467.788 | H11: =G11*(1+Assumptions!H43) -> 89614.567
C12: Google Cloud | D12: =Historicals!H12+(Historicals!F12-Historicals!G12)*(1+Assumptions!D48) -> 100591.7 | E12: =D12*(1+Assumptions!E48) -> 150887.55 | F12: =E12*(1+Assumptions!F48) -> 203698.19 | G12: =F12*(1+Assumptions!G48) -> 260733.69 | H12: =G12*(1+Assumptions!H48) -> 318095.1
C13: Other Bets | D13: =Historicals!H13+(Historicals!F13-Historicals!G13)*(1+Assumptions!D53) -> 1578.4 | E13: =D13*(1+Assumptions!E53) -> 1815.16 | F13: =E13*(1+Assumptions!F53) -> 2087.434 | G13: =F13*(1+Assumptions!G53) -> 2400.5491 | H13: =G13*(1+Assumptions!H53) -> 2760.6315
C14: Hedging gains / (losses) | D14: =Historicals!H14+Assumptions!$D$23 -> -74 | E14: =Assumptions!$D$23 -> 0 | F14: =Assumptions!$D$23 -> 0 | G14: =Assumptions!$D$23 -> 0 | H14: =Assumptions!$D$23 -> 0
C15: Total revenue | D15: =SUM(D8:D14) -> 495071.26 | E15: =SUM(E8:E14) -> 590432.8 | F15: =SUM(F8:F14) -> 686585.66 | G15: =SUM(G8:G14) -> 784173.86 | H15: =SUM(H8:H14) -> 880073.9
C19: Search & other EBIT | D19: =D8*Assumptions!D58 -> 107605.48 | E19: =E8*Assumptions!E58 -> 120518.14 | F19: =F8*Assumptions!F58 -> 135803.37 | G19: =G8*Assumptions!G58 -> 146667.64 | H19: =H8*Assumptions!H58 -> 156934.37
C20: YouTube ads EBIT | D20: =D9*Assumptions!D58 -> 18612.245 | E20: =E9*Assumptions!E58 -> 20845.715 | F20: =F9*Assumptions!F58 -> 23703.103 | G20: =G9*Assumptions!G58 -> 26073.413 | H20: =H9*Assumptions!H58 -> 28420.02
C21: Network EBIT | D21: =D10*Assumptions!D58 -> 11952.468 | E21: =E10*Assumptions!E58 -> 11713.418 | F21: =F10*Assumptions!F58 -> 11879.12 | G21: =G10*Assumptions!G58 -> 11879.12 | H21: =H10*Assumptions!H58 -> 11879.12
C22: Subscriptions & devices EBIT | D22: =D11*Assumptions!D58 -> 22949.619 | E22: =E11*Assumptions!E58 -> 26392.062 | F22: =F11*Assumptions!F58 -> 30550.421 | G22: =G11*Assumptions!G58 -> 34216.471 | H22: =H11*Assumptions!H58 -> 37638.118
C23: Google Cloud EBIT | D23: =D12*Assumptions!D63 -> 34201.178 | E23: =E12*Assumptions!E63 -> 49792.891 | F23: =F12*Assumptions!F63 -> 69257.385 | G23: =G12*Assumptions!G63 -> 91256.79 | H23: =H12*Assumptions!H63 -> 114514.24
C24: Other Bets EBIT | D24: =D13*Assumptions!D68 -> -7102.8 | E24: =E13*Assumptions!E68 -> -7260.64 | F24: =F13*Assumptions!F68 -> -6262.302 | G24: =G13*Assumptions!G68 -> -4801.0982 | H24: =H13*Assumptions!H68 -> -2760.6315
C25: Alphabet-level costs | D25: =-D15*Assumptions!D73 -> -24753.563 | E25: =-E15*Assumptions!E73 -> -29521.64 | F25: =-F15*Assumptions!F73 -> -30896.355 | G25: =-G15*Assumptions!G73 -> -31366.955 | H25: =-H15*Assumptions!H73 -> -35202.956
C26: Operating income | D26: =SUM(D19:D25) -> 163464.63 | E26: =SUM(E19:E25) -> 192479.95 | F26: =SUM(F19:F25) -> 234034.74 | G26: =SUM(G19:G25) -> 273925.38 | H26: =SUM(H19:H25) -> 311422.28
C27: Operating margin | D27: =D26/D15 -> 0.33018404 | E27: =E26/E15 -> 0.32599806 | F27: =F26/F15 -> 0.34086751 | G27: =G26/G15 -> 0.34931715 | H27: =H26/H15 -> 0.35385924
C29: Normalized operating tax | D29: =D26*Assumptions!$D$13 -> 32692.926 | E29: =E26*Assumptions!$D$13 -> 38495.99 | F29: =F26*Assumptions!$D$13 -> 46806.948 | G29: =G26*Assumptions!$D$13 -> 54785.076 | H29: =H26*Assumptions!$D$13 -> 62284.456
C30: NOPAT | D30: =D26-D29 -> 130771.7 | E30: =E26-E29 -> 153983.96 | F30: =F26-F29 -> 187227.79 | G30: =G26-G29 -> 219140.31 | H30: =H26-H29 -> 249137.82
C32: D&A | D32: =D15*Assumptions!D78 -> 34654.988 | E32: =E15*Assumptions!E78 -> 59043.28 | F32: =F15*Assumptions!F78 -> 82390.279 | G32: =G15*Assumptions!G78 -> 101942.6 | H32: =H15*Assumptions!H78 -> 114409.61
C33: Cash capex | D33: =Assumptions!$D$19 -> 200000 | E33: =E15*Assumptions!E83 -> 271599.09 | F33: =F15*Assumptions!F83 -> 247170.84 | G33: =G15*Assumptions!G83 -> 203885.2 | H33: =H15*Assumptions!H83 -> 167214.04
C34: Capex / revenue | D34: =D33/D15 -> 0.40398225 | E34: =E33/E15 -> 0.46 | F34: =F33/F15 -> 0.36 | G34: =G33/G15 -> 0.26 | H34: =H33/H15 -> 0.19
C36: Ending trade NWC | D36: =D15*Assumptions!D88 -> 49507.126 | E36: =E15*Assumptions!E88 -> 59043.28 | F36: =F15*Assumptions!F88 -> 68658.566 | G36: =G15*Assumptions!G88 -> 78417.386 | H36: =H15*Assumptions!H88 -> 88007.39
C37: Beginning trade NWC | D37: =Historicals!F40 -> 46547 | E37: =D36 -> 49507.126 | F37: =E36 -> 59043.28 | G37: =F36 -> 68658.566 | H37: =G36 -> 78417.386
C38: Change in trade NWC | D38: =D36-D37 -> 2960.126 | E38: =E36-E37 -> 9536.1539 | F38: =F36-F37 -> 9615.286 | G38: =G36-G37 -> 9758.8205 | H38: =H36-H37 -> 9590.0039
C40: Unlevered free cash flow | D40: =D30+D32-D33-D38 -> -37533.433 | E40: =E30+E32-E33-E38 -> -68108.003 | F40: =F30+F32-F33-F38 -> 12831.95 | G40: =G30+G32-G33-G38 -> 107438.88 | H40: =H30+H32-H33-H38 -> 186743.39
C41: EBITDA (forecast) | D41: =D26+D32 -> 198119.62 | E41: =E26+E32 -> 251523.23 | F41: =F26+F32 -> 316425.02 | G41: =G26+G32 -> 375867.98 | H41: =H26+H32 -> 425831.89
C43: D&A and capex allocations are teaching assumptions. The capex test holds revenue and D&A drivers fixed.
C46: Search & other cash-flow allocation
C47: Revenue allocation weight | D47: =D8/SUM(D$8:D$13) -> 0.53005132 | E47: =E8/SUM(E$8:E$13) -> 0.49784952 | F47: =F8/SUM(F$8:F$13) -> 0.47094103 | G47: =G8/SUM(G$8:G$13) -> 0.44532046 | H47: =H8/SUM(H$8:H$13) -> 0.42457034
C48: Allocated D&A | D48: =D$32*D47 -> 18368.922 | E48: =E$32*E47 -> 29394.669 | F48: =F$32*F47 -> 38800.963 | G48: =G$32*G47 -> 45397.126 | H48: =H$32*H47 -> 48574.925
C49: Allocated capex | D49: =D$33*D47 -> 106010.26 | E49: =E$33*E47 -> 135215.48 | F49: =F$33*F47 -> 116402.89 | G49: =G$33*G47 -> 90794.253 | H49: =H$33*H47 -> 70994.122
C50: Allocated trade ΔNWC | D50: =D$38*D47 -> 1569.0187 | E50: =E$38*E47 -> 4747.5697 | F50: =F$38*F47 -> 4528.2327 | G50: =G$38*G47 -> 4345.8024 | H50: =H$38*H47 -> 4071.6312
C51: Allocated unlevered cash flow | D51: =D19*(1-Assumptions!$D$13)+D48-D49-D50 -> -3125.9737 | E51: =E19*(1-Assumptions!$D$13)+E48-E49-E50 -> -14153.864 | F51: =F19*(1-Assumptions!$D$13)+F48-F49-F50 -> 26512.538 | G51: =G19*(1-Assumptions!$D$13)+G48-G49-G50 -> 67591.183 | H51: =H19*(1-Assumptions!$D$13)+H48-H49-H50 -> 99056.672
C53: YouTube ads cash-flow allocation
C54: Revenue allocation weight | D54: =D9/SUM(D$8:D$13) -> 0.091681621 | E54: =E9/SUM(E$8:E$13) -> 0.086111758 | F54: =F9/SUM(F$8:F$13) -> 0.082197987 | G54: =G9/SUM(G$8:G$13) -> 0.07916555 | H54: =H9/SUM(H$8:H$13) -> 0.076887537
C55: Allocated D&A | D55: =D$32*D54 -> 3177.2255 | E55: =E$32*E54 -> 5084.3206 | F55: =F$32*F54 -> 6772.3151 | G55: =G$32*G54 -> 8070.3422 | H55: =H$32*H54 -> 8796.6729
C56: Allocated capex | D56: =D$33*D54 -> 18336.324 | E56: =E$33*E54 -> 23387.875 | F56: =F$33*F54 -> 20316.945 | G56: =G$33*G54 -> 16140.684 | H56: =H$33*H54 -> 12856.676
C57: Allocated trade ΔNWC | D57: =D$38*D54 -> 271.38915 | E57: =E$38*E54 -> 821.17498 | F57: =F$38*F54 -> 790.35715 | G57: =G$38*G54 -> 772.56239 | H57: =H$38*H54 -> 737.35178
C58: Allocated unlevered cash flow | D58: =D20*(1-Assumptions!$D$13)+D55-D56-D57 -> -540.69167 | E58: =E20*(1-Assumptions!$D$13)+E55-E56-E57 -> -2448.1576 | F58: =F20*(1-Assumptions!$D$13)+F55-F56-F57 -> 4627.4949 | G58: =G20*(1-Assumptions!$D$13)+G55-G56-G57 -> 12015.826 | H58: =H20*(1-Assumptions!$D$13)+H55-H56-H57 -> 17938.662
C60: Network cash-flow allocation
C61: Revenue allocation weight | D61: =D10/SUM(D$8:D$13) -> 0.058876379 | E61: =E10/SUM(E$8:E$13) -> 0.048387069 | F61: =F10/SUM(F$8:F$13) -> 0.041194597 | G61: =G10/SUM(G$8:G$13) -> 0.036068047 | H61: =H10/SUM(H$8:H$13) -> 0.032137778
C62: Allocated D&A | D62: =D$32*D61 -> 2040.3602 | E62: =E$32*E61 -> 2856.9313 | F62: =F$32*F61 -> 3394.0344 | G62: =G$32*G61 -> 3676.8706 | H62: =H$32*H61 -> 3676.8706
C63: Allocated capex | D63: =D$33*D61 -> 11775.276 | E63: =E$33*E61 -> 13141.884 | F63: =F$33*F61 -> 10182.103 | G63: =G$33*G61 -> 7353.7411 | H63: =H$33*H61 -> 5373.8877
C64: Allocated trade ΔNWC | D64: =D$38*D61 -> 174.2815 | E64: =E$38*E61 -> 461.42654 | F64: =F$38*F61 -> 396.09783 | G64: =G$38*G61 -> 351.9816 | H64: =H$38*H61 -> 308.20142
C65: Allocated unlevered cash flow | D65: =D21*(1-Assumptions!$D$13)+D62-D63-D64 -> -347.223 | E65: =E21*(1-Assumptions!$D$13)+E62-E63-E64 -> -1375.6446 | F65: =F21*(1-Assumptions!$D$13)+F62-F63-F64 -> 2319.1297 | G65: =G21*(1-Assumptions!$D$13)+G62-G63-G64 -> 5474.4441 | H65: =H21*(1-Assumptions!$D$13)+H62-H63-H64 -> 7498.0776
C67: Subscriptions & devices cash-flow allocation
C68: Revenue allocation weight | D68: =D11/SUM(D$8:D$13) -> 0.11304699 | E68: =E11/SUM(E$8:E$13) -> 0.10902321 | F68: =F11/SUM(F$8:F$13) -> 0.10594322 | G68: =G11/SUM(G$8:G$13) -> 0.10388996 | H68: =H11/SUM(H$8:H$13) -> 0.10182618
C69: Allocated D&A | D69: =D$32*D68 -> 3917.642 | E69: =E$32*E68 -> 6437.0882 | F69: =F$32*F68 -> 8728.6916 | G69: =G$32*G68 -> 10590.812 | H69: =H$32*H68 -> 11649.894
C70: Allocated capex | D70: =D$33*D68 -> 22609.397 | E70: =E$33*E68 -> 29610.606 | F70: =F$33*F68 -> 26186.075 | G70: =G$33*G68 -> 21181.625 | H70: =H$33*H68 -> 17026.768
C71: Allocated trade ΔNWC | D71: =D$38*D68 -> 334.63333 | E71: =E$38*E68 -> 1039.6622 | F71: =F$38*F68 -> 1018.6744 | G71: =G$38*G68 -> 1013.8434 | H71: =H$38*H68 -> 976.5135
C72: Allocated unlevered cash flow | D72: =D22*(1-Assumptions!$D$13)+D69-D70-D71 -> -666.69376 | E72: =E22*(1-Assumptions!$D$13)+E69-E70-E71 -> -3099.5304 | F72: =F22*(1-Assumptions!$D$13)+F69-F70-F71 -> 5964.2789 | G72: =G22*(1-Assumptions!$D$13)+G69-G70-G71 -> 15768.521 | H72: =H22*(1-Assumptions!$D$13)+H69-H70-H71 -> 23757.107
C74: Google Cloud cash-flow allocation
C75: Revenue allocation weight | D75: =D12/SUM(D$8:D$13) -> 0.20315594 | E75: =E12/SUM(E$8:E$13) -> 0.25555415 | F75: =F12/SUM(F$8:F$13) -> 0.29668285 | G75: =G12/SUM(G$8:G$13) -> 0.33249474 | H75: =H12/SUM(H$8:H$13) -> 0.36144135
C76: Allocated D&A | D76: =D$32*D75 -> 7040.3667 | E76: =E$32*E75 -> 15088.755 | F76: =F$32*F75 -> 24443.783 | G76: =G$32*G75 -> 33895.379 | H76: =H$32*H75 -> 41352.363
C77: Allocated capex | D77: =D$33*D75 -> 40631.188 | E77: =E$33*E75 -> 69408.273 | F77: =F$33*F75 -> 73331.349 | G77: =G$33*G75 -> 67790.758 | H77: =H$33*H75 -> 60438.069
C78: Allocated trade ΔNWC | D78: =D$38*D75 -> 601.36718 | E78: =E$38*E75 -> 2437.0037 | F78: =F$38*F75 -> 2852.6905 | G78: =G$38*G75 -> 3244.7565 | H78: =H$38*H75 -> 3466.2239
C79: Allocated unlevered cash flow | D79: =D23*(1-Assumptions!$D$13)+D76-D77-D78 -> -6831.2458 | E79: =E23*(1-Assumptions!$D$13)+E76-E77-E78 -> -16922.208 | F79: =F23*(1-Assumptions!$D$13)+F76-F77-F78 -> 3665.6517 | G79: =G23*(1-Assumptions!$D$13)+G76-G77-G78 -> 35865.296 | H79: =H23*(1-Assumptions!$D$13)+H76-H77-H78 -> 69059.458
C81: Other Bets cash-flow allocation
C82: Revenue allocation weight | D82: =D13/SUM(D$8:D$13) -> 0.0031877514 | E82: =E13/SUM(E$8:E$13) -> 0.0030742872 | F82: =F13/SUM(F$8:F$13) -> 0.0030403111 | G82: =G13/SUM(G$8:G$13) -> 0.003061246 | H82: =H13/SUM(H$8:H$13) -> 0.0031368178
C83: Allocated D&A | D83: =D$32*D82 -> 110.47149 | E83: =E$32*E82 -> 181.516 | F83: =F$32*F82 -> 250.49208 | G83: =G$32*G82 -> 312.07138 | H83: =H$32*H82 -> 358.88209
C84: Allocated capex | D84: =D$33*D82 -> 637.55028 | E84: =E$33*E82 -> 834.9736 | F84: =F$33*F82 -> 751.47624 | G84: =G$33*G82 -> 624.14277 | H84: =H$33*H82 -> 524.51998
C85: Allocated trade ΔNWC | D85: =D$38*D82 -> 9.4361458 | E85: =E$38*E82 -> 29.316876 | F85: =F$38*F82 -> 29.233461 | G85: =G$38*G82 -> 29.87415 | H85: =H$38*H82 -> 30.082095
C86: Allocated unlevered cash flow | D86: =D24*(1-Assumptions!$D$13)+D83-D84-D85 -> -6218.7549 | E86: =E24*(1-Assumptions!$D$13)+E83-E84-E85 -> -6491.2865 | F86: =F24*(1-Assumptions!$D$13)+F83-F84-F85 -> -5540.0592 | G86: =G24*(1-Assumptions!$D$13)+G83-G84-G85 -> -4182.8241 | H86: =H24*(1-Assumptions!$D$13)+H83-H84-H85 -> -2404.2252
C90: Allocation reconciliation difference | D90: =SUM(D51,D58,D65,D72,D79,D86)+D25*(1-Assumptions!$D$13)-D40 -> 0 | E90: =SUM(E51,E58,E65,E72,E79,E86)+E25*(1-Assumptions!$D$13)-E40 -> 0 | F90: =SUM(F51,F58,F65,F72,F79,F86)+F25*(1-Assumptions!$D$13)-F40 -> 4.3655746e-11 | G90: =SUM(G51,G58,G65,G72,G79,G86)+G25*(1-Assumptions!$D$13)-G40 -> 0 | H90: =SUM(H51,H58,H65,H72,H79,H86)+H25*(1-Assumptions!$D$13)-H40 -> 0
C93: 2026 stub construction
C94: H1 normalized NOPAT | D94: =Historicals!H22*(1-Assumptions!$D$13) -> 64372.8
C95: H1 D&A | D95: =SUM(Historicals!H30,Historicals!H53) -> 14131
C96: H1 cash capex | D96: =Historicals!H33 -> 80598
C97: H1 trade NWC change | D97: =Historicals!H40-Historicals!F40 -> 5207
C98: H1 normalized unlevered FCF | D98: =D94+D95-D96-D97 -> -7301.2
C99: Projected H2 unlevered FCF | D99: =D40-D98 -> -30232.233
C101: H1 normalized unlevered FCF is derived with the assumed operating tax rate. It is not reported free cash flow.

Sheet DCF
C2: DCF
C4: Case selected | D4: =CHOOSE(Assumptions!$D$4,"Base","Bull","Bear") -> Base
C6: Common equity market value | D6: =Assumptions!D7*Historicals!H47 -> 4165415.7
C7: Debt market value proxy | D7: =SUM(Historicals!H45:H46) -> 96586
C8: Preferred market value proxy | D8: =Historicals!H48*Historicals!H49 -> 19250
C9: CAPM cost of common equity | D9: =Assumptions!D9+Assumptions!D10*Assumptions!D11 -> 0.099
C10: After-tax debt cost | D10: =Assumptions!D12*(1-Assumptions!D13) -> 0.0384
C11: Preferred cost | D11: =Assumptions!D20 -> 0.0625
C12: Common equity weight | D12: =D6/SUM(D6:D8) -> 0.97294343
C13: Debt weight | D13: =D7/SUM(D6:D8) -> 0.022560225
C14: Preferred weight | D14: =D8/SUM(D6:D8) -> 0.0044963486
C15: WACC | D15: =SUMPRODUCT(D9:D11,D12:D14) -> 0.097468734
C17: Cash-flow discounting | D17: 2026 stub | E17: 2027E | F17: 2028E | G17: 2029E | H17: 2030E
C18: Period end (exclusive) | D18: 46388 | E18: 46753 | F18: 47119 | G18: 47484 | H18: 47849
C19: Period start | D19: =Assumptions!D6 -> 46312 | E19: =DATE(YEAR(E18)-1,1,1) -> 46388 | F19: =DATE(YEAR(F18)-1,1,1) -> 46753 | G19: =DATE(YEAR(G18)-1,1,1) -> 47119 | H19: =DATE(YEAR(H18)-1,1,1) -> 47484
C20: Remaining years | D20: =(D18-D19)/365 -> 0.20821918 | E20: =(E18-E19)/365 -> 1 | F20: =(F18-F19)/365 -> 1.0027397 | G20: =(G18-G19)/365 -> 1 | H20: =(H18-H19)/365 -> 1
C21: Midpoint discount time | D21: =((D18+D19)/2-Assumptions!D6)/365 -> 0.10410959 | E21: =((E18+E19)/2-Assumptions!D6)/365 -> 0.70821918 | F21: =((F18+F19)/2-Assumptions!D6)/365 -> 1.709589 | G21: =((G18+G19)/2-Assumptions!D6)/365 -> 2.7109589 | H21: =((H18+H19)/2-Assumptions!D6)/365 -> 3.7109589
C22: Full-year forecast FCF | D22: =Projections!D40 -> -37533.433 | E22: =Projections!E40 -> -68108.003 | F22: =Projections!F40 -> 12831.95 | G22: =Projections!G40 -> 107438.88 | H22: =Projections!H40 -> 186743.39
C23: Cash flow valued | D23: =Projections!D99*(D18-D19)/(D18-DATE(2026,7,1)) -> -12487.227 | E23: =E22 -> -68108.003 | F23: =F22 -> 12831.95 | G23: =G22 -> 107438.88 | H23: =H22 -> 186743.39
C24: Discount factor | D24: =1/(1+$D$15)^D21 -> 0.99036387 | E24: =1/(1+$D$15)^E21 -> 0.9362536 | F24: =1/(1+$D$15)^F21 -> 0.85299407 | G24: =1/(1+$D$15)^G21 -> 0.77713868 | H24: =1/(1+$D$15)^H21 -> 0.7081192
C25: Present value of cash flow | D25: =D23*D24 -> -12366.898 | E25: =E23*E24 -> -63766.363 | F25: =F23*F24 -> 10945.577 | G25: =G23*G24 -> 83494.911 | H25: =H23*H24 -> 132236.58
C29: 2031 revenue | D29: =Projections!H15*(1+Assumptions!D14) -> 906476.12
C30: 2031 NOPAT | D30: =Projections!H30*(1+Assumptions!D14) -> 256611.96
C31: 2031 D&A | D31: =Projections!H32*(1+Assumptions!D14) -> 117841.9
C32: 2031 normalized capex | D32: =D31*Assumptions!D15 -> 135518.18
C33: 2031 change in trade NWC | D33: =Projections!H36*Assumptions!D14 -> 2640.2217
C34: Normalized terminal FCF | D34: =D30+D31-D32-D33 -> 236295.45
C35: Terminal value at end 2030 | D35: =D34/(D15-Assumptions!D14) -> 3502295.7
C36: Terminal discount time | D36: =(H18-Assumptions!D6)/365 -> 4.2109589
C37: Present value of terminal value | D37: =D35/(1+D15)^D36 -> 2367353.4
C38: Present value of explicit FCF | D38: =SUM(D25:H25) -> 150543.8
C39: Enterprise value | D39: =SUM(D37:D38) -> 2517897.2
C40: Terminal PV / enterprise value | D40: =D37/D39 -> 0.9402105
C42: Cash and marketable securities | D42: =Historicals!H42 -> 242474
C43: Debt carrying value deduction | D43: =-SUM(Historicals!H43:H44) -> -100164
C44: Preferred preference deduction | D44: =-D8 -> -19250
C45: Recognized non-marketable stakes | D45: =Historicals!H50*Assumptions!D16 -> 0
C46: Deferred tax liability deduction | D46: =-Historicals!H51 -> -22819
C47: Accrued legal claims deduction | D47: =-Historicals!H52 -> -17400
C48: Net equity bridge adjustment | D48: =SUM(D42:D47) -> 82841
C49: Common equity value | D49: =D39+D48 -> 2600738.2
C50: Common shares, millions | D50: =Historicals!H47 -> 12230
C51: Value per common share | D51: =D49/D50 -> 212.65235
C52: Return vs closing price | D52: =D51/Assumptions!D7-1 -> -0.37563538
C55: June balance sheet is held constant to the valuation date. Preferred conversion and equity-tax timing are simplified.

Sheet Sensitivity
C2: Sensitivity
C4: Case selected | D4: =CHOOSE(Assumptions!$D$4,"Base","Bull","Bear") -> Base
C6: WACC rows and perpetual growth columns. Same selected operating case; normalized terminal capex in every cell.
C9: WACC / terminal growth | D9: =Assumptions!D14+(0-2)*Assumptions!D22 -> 0.02 | E9: =Assumptions!D14+(1-2)*Assumptions!D22 -> 0.025 | F9: =Assumptions!D14+(2-2)*Assumptions!D22 -> 0.03 | G9: =Assumptions!D14+(3-2)*Assumptions!D22 -> 0.035 | H9: =Assumptions!D14+(4-2)*Assumptions!D22 -> 0.04
C10: =DCF!D15+(0-3)*Assumptions!D21 -> 0.082468734 | D10: =(SUMPRODUCT(DCF!$D$23:$H$23,1/(1+$C10)^DCF!$D$21:$H$21)+((Projections!$H$30+Projections!$H$32*(1-Assumptions!$D$15))*(1+D$9)-Projections!$H$36*D$9)/($C10-D$9)/(1+$C10)^DCF!$D$36+DCF!$D$48)/DCF!$D$50 -> 240.06418 | E10: =(SUMPRODUCT(DCF!$D$23:$H$23,1/(1+$C10)^DCF!$D$21:$H$21)+((Projections!$H$30+Projections!$H$32*(1-Assumptions!$D$15))*(1+E$9)-Projections!$H$36*E$9)/($C10-E$9)/(1+$C10)^DCF!$D$36+DCF!$D$48)/DCF!$D$50 -> 259.95483 | F10: =(SUMPRODUCT(DCF!$D$23:$H$23,1/(1+$C10)^DCF!$D$21:$H$21)+((Projections!$H$30+Projections!$H$32*(1-Assumptions!$D$15))*(1+F$9)-Projections!$H$36*F$9)/($C10-F$9)/(1+$C10)^DCF!$D$36+DCF!$D$48)/DCF!$D$50 -> 283.63644 | G10: =(SUMPRODUCT(DCF!$D$23:$H$23,1/(1+$C10)^DCF!$D$21:$H$21)+((Projections!$H$30+Projections!$H$32*(1-Assumptions!$D$15))*(1+G$9)-Projections!$H$36*G$9)/($C10-G$9)/(1+$C10)^DCF!$D$36+DCF!$D$48)/DCF!$D$50 -> 312.30694 | H10: =(SUMPRODUCT(DCF!$D$23:$H$23,1/(1+$C10)^DCF!$D$21:$H$21)+((Projections!$H$30+Projections!$H$32*(1-Assumptions!$D$15))*(1+H$9)-Projections!$H$36*H$9)/($C10-H$9)/(1+$C10)^DCF!$D$36+DCF!$D$48)/DCF!$D$50 -> 347.7284
C11: =DCF!D15+(1-3)*Assumptions!D21 -> 0.087468734 | D11: =(SUMPRODUCT(DCF!$D$23:$H$23,1/(1+$C11)^DCF!$D$21:$H$21)+((Projections!$H$30+Projections!$H$32*(1-Assumptions!$D$15))*(1+D$9)-Projections!$H$36*D$9)/($C11-D$9)/(1+$C11)^DCF!$D$36+DCF!$D$48)/DCF!$D$50 -> 219.55792 | E11: =(SUMPRODUCT(DCF!$D$23:$H$23,1/(1+$C11)^DCF!$D$21:$H$21)+((Projections!$H$30+Projections!$H$32*(1-Assumptions!$D$15))*(1+E$9)-Projections!$H$36*E$9)/($C11-E$9)/(1+$C11)^DCF!$D$36+DCF!$D$48)/DCF!$D$50 -> 236.22388 | F11: =(SUMPRODUCT(DCF!$D$23:$H$23,1/(1+$C11)^DCF!$D$21:$H$21)+((Projections!$H$30+Projections!$H$32*(1-Assumptions!$D$15))*(1+F$9)-Projections!$H$36*F$9)/($C11-F$9)/(1+$C11)^DCF!$D$36+DCF!$D$48)/DCF!$D$50 -> 255.78985 | G11: =(SUMPRODUCT(DCF!$D$23:$H$23,1/(1+$C11)^DCF!$D$21:$H$21)+((Projections!$H$30+Projections!$H$32*(1-Assumptions!$D$15))*(1+G$9)-Projections!$H$36*G$9)/($C11-G$9)/(1+$C11)^DCF!$D$36+DCF!$D$48)/DCF!$D$50 -> 279.08489 | H11: =(SUMPRODUCT(DCF!$D$23:$H$23,1/(1+$C11)^DCF!$D$21:$H$21)+((Projections!$H$30+Projections!$H$32*(1-Assumptions!$D$15))*(1+H$9)-Projections!$H$36*H$9)/($C11-H$9)/(1+$C11)^DCF!$D$36+DCF!$D$48)/DCF!$D$50 -> 307.28738
C12: =DCF!D15+(2-3)*Assumptions!D21 -> 0.092468734 | D12: =(SUMPRODUCT(DCF!$D$23:$H$23,1/(1+$C12)^DCF!$D$21:$H$21)+((Projections!$H$30+Projections!$H$32*(1-Assumptions!$D$15))*(1+D$9)-Projections!$H$36*D$9)/($C12-D$9)/(1+$C12)^DCF!$D$36+DCF!$D$48)/DCF!$D$50 -> 201.93594 | E12: =(SUMPRODUCT(DCF!$D$23:$H$23,1/(1+$C12)^DCF!$D$21:$H$21)+((Projections!$H$30+Projections!$H$32*(1-Assumptions!$D$15))*(1+E$9)-Projections!$H$36*E$9)/($C12-E$9)/(1+$C12)^DCF!$D$36+DCF!$D$48)/DCF!$D$50 -> 216.06879 | F12: =(SUMPRODUCT(DCF!$D$23:$H$23,1/(1+$C12)^DCF!$D$21:$H$21)+((Projections!$H$30+Projections!$H$32*(1-Assumptions!$D$15))*(1+F$9)-Projections!$H$36*F$9)/($C12-F$9)/(1+$C12)^DCF!$D$36+DCF!$D$48)/DCF!$D$50 -> 232.46402 | G12: =(SUMPRODUCT(DCF!$D$23:$H$23,1/(1+$C12)^DCF!$D$21:$H$21)+((Projections!$H$30+Projections!$H$32*(1-Assumptions!$D$15))*(1+G$9)-Projections!$H$36*G$9)/($C12-G$9)/(1+$C12)^DCF!$D$36+DCF!$D$48)/DCF!$D$50 -> 251.71215 | H12: =(SUMPRODUCT(DCF!$D$23:$H$23,1/(1+$C12)^DCF!$D$21:$H$21)+((Projections!$H$30+Projections!$H$32*(1-Assumptions!$D$15))*(1+H$9)-Projections!$H$36*H$9)/($C12-H$9)/(1+$C12)^DCF!$D$36+DCF!$D$48)/DCF!$D$50 -> 274.62877
C13: =DCF!D15+(3-3)*Assumptions!D21 -> 0.097468734 | D13: =(SUMPRODUCT(DCF!$D$23:$H$23,1/(1+$C13)^DCF!$D$21:$H$21)+((Projections!$H$30+Projections!$H$32*(1-Assumptions!$D$15))*(1+D$9)-Projections!$H$36*D$9)/($C13-D$9)/(1+$C13)^DCF!$D$36+DCF!$D$48)/DCF!$D$50 -> 186.63844 | E13: =(SUMPRODUCT(DCF!$D$23:$H$23,1/(1+$C13)^DCF!$D$21:$H$21)+((Projections!$H$30+Projections!$H$32*(1-Assumptions!$D$15))*(1+E$9)-Projections!$H$36*E$9)/($C13-E$9)/(1+$C13)^DCF!$D$36+DCF!$D$48)/DCF!$D$50 -> 198.74798 | F13: =(SUMPRODUCT(DCF!$D$23:$H$23,1/(1+$C13)^DCF!$D$21:$H$21)+((Projections!$H$30+Projections!$H$32*(1-Assumptions!$D$15))*(1+F$9)-Projections!$H$36*F$9)/($C13-F$9)/(1+$C13)^DCF!$D$36+DCF!$D$48)/DCF!$D$50 -> 212.65235 | G13: =(SUMPRODUCT(DCF!$D$23:$H$23,1/(1+$C13)^DCF!$D$21:$H$21)+((Projections!$H$30+Projections!$H$32*(1-Assumptions!$D$15))*(1+G$9)-Projections!$H$36*G$9)/($C13-G$9)/(1+$C13)^DCF!$D$36+DCF!$D$48)/DCF!$D$50 -> 228.78253 | H13: =(SUMPRODUCT(DCF!$D$23:$H$23,1/(1+$C13)^DCF!$D$21:$H$21)+((Projections!$H$30+Projections!$H$32*(1-Assumptions!$D$15))*(1+H$9)-Projections!$H$36*H$9)/($C13-H$9)/(1+$C13)^DCF!$D$36+DCF!$D$48)/DCF!$D$50 -> 247.71949
C14: =DCF!D15+(4-3)*Assumptions!D21 -> 0.10246873 | D14: =(SUMPRODUCT(DCF!$D$23:$H$23,1/(1+$C14)^DCF!$D$21:$H$21)+((Projections!$H$30+Projections!$H$32*(1-Assumptions!$D$15))*(1+D$9)-Projections!$H$36*D$9)/($C14-D$9)/(1+$C14)^DCF!$D$36+DCF!$D$48)/DCF!$D$50 -> 173.24142 | E14: =(SUMPRODUCT(DCF!$D$23:$H$23,1/(1+$C14)^DCF!$D$21:$H$21)+((Projections!$H$30+Projections!$H$32*(1-Assumptions!$D$15))*(1+E$9)-Projections!$H$36*E$9)/($C14-E$9)/(1+$C14)^DCF!$D$36+DCF!$D$48)/DCF!$D$50 -> 183.71138 | F14: =(SUMPRODUCT(DCF!$D$23:$H$23,1/(1+$C14)^DCF!$D$21:$H$21)+((Projections!$H$30+Projections!$H$32*(1-Assumptions!$D$15))*(1+F$9)-Projections!$H$36*F$9)/($C14-F$9)/(1+$C14)^DCF!$D$36+DCF!$D$48)/DCF!$D$50 -> 195.62609 | G14: =(SUMPRODUCT(DCF!$D$23:$H$23,1/(1+$C14)^DCF!$D$21:$H$21)+((Projections!$H$30+Projections!$H$32*(1-Assumptions!$D$15))*(1+G$9)-Projections!$H$36*G$9)/($C14-G$9)/(1+$C14)^DCF!$D$36+DCF!$D$48)/DCF!$D$50 -> 209.30675 | H14: =(SUMPRODUCT(DCF!$D$23:$H$23,1/(1+$C14)^DCF!$D$21:$H$21)+((Projections!$H$30+Projections!$H$32*(1-Assumptions!$D$15))*(1+H$9)-Projections!$H$36*H$9)/($C14-H$9)/(1+$C14)^DCF!$D$36+DCF!$D$48)/DCF!$D$50 -> 225.17743
C15: =DCF!D15+(5-3)*Assumptions!D21 -> 0.10746873 | D15: =(SUMPRODUCT(DCF!$D$23:$H$23,1/(1+$C15)^DCF!$D$21:$H$21)+((Projections!$H$30+Projections!$H$32*(1-Assumptions!$D$15))*(1+D$9)-Projections!$H$36*D$9)/($C15-D$9)/(1+$C15)^DCF!$D$36+DCF!$D$48)/DCF!$D$50 -> 161.41787 | E15: =(SUMPRODUCT(DCF!$D$23:$H$23,1/(1+$C15)^DCF!$D$21:$H$21)+((Projections!$H$30+Projections!$H$32*(1-Assumptions!$D$15))*(1+E$9)-Projections!$H$36*E$9)/($C15-E$9)/(1+$C15)^DCF!$D$36+DCF!$D$48)/DCF!$D$50 -> 170.54235 | F15: =(SUMPRODUCT(DCF!$D$23:$H$23,1/(1+$C15)^DCF!$D$21:$H$21)+((Projections!$H$30+Projections!$H$32*(1-Assumptions!$D$15))*(1+F$9)-Projections!$H$36*F$9)/($C15-F$9)/(1+$C15)^DCF!$D$36+DCF!$D$48)/DCF!$D$50 -> 180.84466 | G15: =(SUMPRODUCT(DCF!$D$23:$H$23,1/(1+$C15)^DCF!$D$21:$H$21)+((Projections!$H$30+Projections!$H$32*(1-Assumptions!$D$15))*(1+G$9)-Projections!$H$36*G$9)/($C15-G$9)/(1+$C15)^DCF!$D$36+DCF!$D$48)/DCF!$D$50 -> 192.56859 | H15: =(SUMPRODUCT(DCF!$D$23:$H$23,1/(1+$C15)^DCF!$D$21:$H$21)+((Projections!$H$30+Projections!$H$32*(1-Assumptions!$D$15))*(1+H$9)-Projections!$H$36*H$9)/($C15-H$9)/(1+$C15)^DCF!$D$36+DCF!$D$48)/DCF!$D$50 -> 206.03021
C16: =DCF!D15+(6-3)*Assumptions!D21 -> 0.11246873 | D16: =(SUMPRODUCT(DCF!$D$23:$H$23,1/(1+$C16)^DCF!$D$21:$H$21)+((Projections!$H$30+Projections!$H$32*(1-Assumptions!$D$15))*(1+D$9)-Projections!$H$36*D$9)/($C16-D$9)/(1+$C16)^DCF!$D$36+DCF!$D$48)/DCF!$D$50 -> 150.91152 | E16: =(SUMPRODUCT(DCF!$D$23:$H$23,1/(1+$C16)^DCF!$D$21:$H$21)+((Projections!$H$30+Projections!$H$32*(1-Assumptions!$D$15))*(1+E$9)-Projections!$H$36*E$9)/($C16-E$9)/(1+$C16)^DCF!$D$36+DCF!$D$48)/DCF!$D$50 -> 158.91956 | F16: =(SUMPRODUCT(DCF!$D$23:$H$23,1/(1+$C16)^DCF!$D$21:$H$21)+((Projections!$H$30+Projections!$H$32*(1-Assumptions!$D$15))*(1+F$9)-Projections!$H$36*F$9)/($C16-F$9)/(1+$C16)^DCF!$D$36+DCF!$D$48)/DCF!$D$50 -> 167.89864 | G16: =(SUMPRODUCT(DCF!$D$23:$H$23,1/(1+$C16)^DCF!$D$21:$H$21)+((Projections!$H$30+Projections!$H$32*(1-Assumptions!$D$15))*(1+G$9)-Projections!$H$36*G$9)/($C16-G$9)/(1+$C16)^DCF!$D$36+DCF!$D$48)/DCF!$D$50 -> 178.03678 | H16: =(SUMPRODUCT(DCF!$D$23:$H$23,1/(1+$C16)^DCF!$D$21:$H$21)+((Projections!$H$30+Projections!$H$32*(1-Assumptions!$D$15))*(1+H$9)-Projections!$H$36*H$9)/($C16-H$9)/(1+$C16)^DCF!$D$36+DCF!$D$48)/DCF!$D$50 -> 189.57388
C19: Grid center minus DCF | D19: =F13-DCF!D51 -> 0
C21: Price | D21: =Assumptions!D7 -> 340.59
C22: Required terminal FCF at base WACC | D22: =(Assumptions!D7*DCF!D50-DCF!D48-DCF!D38)*(1+DCF!D15)^DCF!D36*(DCF!D15-Assumptions!D14) -> 392472.46
C23: Required / modeled terminal FCF | D23: =D22/DCF!D34 -> 1.6609395

Sheet Multiples
C2: Multiples
C4: Case selected | D4: =CHOOSE(Assumptions!$D$4,"Base","Bull","Bear") -> Base
C6: Peer inputs | D6: GOOGL | E6: MSFT | F6: META | G6: AMZN | J6: Quotes 2026-10-16; financials TTM through 2026-06-30. USD millions.
C8: Closing price | D8: 340.59 | E8: 529.05 | F8: 709.32 | G8: 250 | J8: Q1 / Q2 / Q3 / Q4. Google Finance vendor displays; exchange-direct unavailable.
C9: Common shares, millions | D9: 12230 | E9: 7427 | F9: 2543 | G9: 10783 | J9: S2 all Alphabet classes; S4 Microsoft period end; S5 Meta Q2 basic weighted-average proxy; S7 Amazon period end.
C10: Equity market value proxy | D10: =D8*D9 -> 4165415.7 | E10: =E8*E9 -> 3929254.3 | F10: =F8*F9 -> 1803800.8 | G10: =G8*G9 -> 2695750
C11: Cash & equivalents | D11: 55911 | E11: 20935 | F11: 15462 | G11: 78213 | J11: S2 / S4 / S5 / S7 balance sheets, 2026-06-30.
C12: Marketable securities | D12: 186563 | E12: 55908 | F12: 74798 | G12: 44775 | J12: S2 / S4 / S5 / S7 balance sheets, 2026-06-30.
C13: Debt non-current | D13: 98165 | E13: 31067 | F13: 83664 | G13: 128894 | J13: S2 / S4 / S5 / S9 balance sheets. Excludes leases.
C14: Debt current | D14: 1999 | E14: 9227 | F14: 0 | G14: 3330 | J14: S2 / S4 / S5 no separate current debt disclosed / S9 Note 5.
C15: Preferred liquidation preference | D15: 19250 | E15: 0 | F15: 0 | G15: 0 | J15: S2 mandatory convertible preference; S4 / S5 / S7 no preferred claim reported.
C16: Enterprise value (excludes leases) | D16: =D10+SUM(D13:D15)-SUM(D11:D12) -> 4042355.7 | E16: =E10+SUM(E13:E15)-SUM(E11:E12) -> 3892705.3 | F16: =F10+SUM(F13:F15)-SUM(F11:F12) -> 1797204.8 | G16: =G10+SUM(G13:G15)-SUM(G11:G12) -> 2704986
C20: FY2025 revenue | D20: 402836 | F20: 200966 | G20: 716924 | J20: S1 / S6 / S8 calendar 2025. Microsoft direct TTM input below.
C21: H1 2025 revenue | D21: 186662 | F21: 89830 | G21: 323369 | J21: S2 / S5 / S7, matched prior six months.
C22: H1 2026 revenue | D22: 229692 | F22: 117111 | G22: 382125 | J22: S2 / S5 / S7, six months ended June 30.
C23: TTM revenue | D23: =D20-D21+D22 -> 445866 | E23: =E40 -> 331839 | F23: =F20-F21+F22 -> 228247 | G23: =G20-G21+G22 -> 775680
C25: FY2025 operating income | D25: 129039 | F25: 83276 | G25: 79975 | J25: S1 / S6 / S8.
C26: H1 2025 operating income | D26: 61877 | F26: 37997 | G26: 37576 | J26: S2 / S5 / S7.
C27: H1 2026 operating income | D27: 80466 | F27: 41647 | G27: 51313 | J27: S2 / S5 / S7.
C28: TTM EBIT | D28: =D25-D26+D27 -> 147628 | E28: =E41 -> 155237 | F28: =F25-F26+F27 -> 86926 | G28: =G25-G26+G27 -> 93712
C30: FY2025 common net income | D30: 132170 | F30: 60458 | G30: 77670 | J30: S1 / S6 / S8, GAAP including investment and tax effects.
C31: H1 2025 common net income | D31: 62736 | F31: 34981 | G31: 35291 | J31: S2 / S5 / S7.
C32: H1 2026 common net income | D32: 174685 | F32: 42621 | G32: 92902 | J32: S2 common earnings after preferred dividends / S5 / S7.
C33: TTM common net income | D33: =D30-D31+D32 -> 244119 | E33: =E42 -> 133749 | F33: =F30-F31+F32 -> 68098 | G33: =G30-G31+G32 -> 135281
C35: FY2025 PPE depreciation | D35: 21136 | F35: 18000 | G35: 41860 | J35: X1 / X3 / X4: us-gaap:Depreciation, calendar FY2025.
C36: H1 2025 PPE depreciation | D36: 9485 | F36: 8120 | G36: 18822 | J36: X1 / X3 / X4: us-gaap:Depreciation, six months ended June 30, 2025.
C37: H1 2026 PPE depreciation | D37: 13586 | F37: 11670 | G37: 26703 | J37: X1 / X3 / X4: us-gaap:Depreciation, six months ended June 30, 2026.
C38: TTM PPE depreciation | D38: =D35-D36+D37 -> 25237 | E38: =E43 -> 34300 | F38: =F35-F36+F37 -> 21550 | G38: =G35-G36+G37 -> 49741
C40: Direct TTM revenue | E40: 331839 | J40: S4 year ended June 30, 2026.
C41: Direct TTM EBIT | E41: 155237 | J41: S4 year ended June 30, 2026.
C42: Direct TTM net income | E42: 133749 | J42: S4 GAAP, year ended June 30, 2026.
C43: Direct TTM PPE depreciation | E43: 34300 | J43: X2: us-gaap:Depreciation, July 1, 2025–June 30, 2026. Broad cash-flow addbacks are excluded.
C45: TTM EBITD (reported inputs) | D45: =D28+D38 -> 172865 | E45: =E28+E38 -> 189537 | F45: =F28+F38 -> 108476 | G45: =G28+G38 -> 143453 | J45: EBIT + PPE depreciation only for all. Reported source arithmetic in rows 35–43; bridge and policy in rows 84–95.
C47: P/E, TTM GAAP | D47: =D10/D33 -> 17.063054 | E47: =E10/E33 -> 29.377822 | F47: =F10/F33 -> 26.488307 | G47: =G10/G33 -> 19.927041
C48: Forward P/E (CY2027 adjusted) | D48: =D8/D77 -> 22.33377 | E48: =E8/E77 -> 24.324138 | F48: =F8/F77 -> 20.482818 | G48: =G8/G77 -> 23.923445 | J48: Price / CY2027 adjusted consensus EPS. See rows 72–82 for dated inputs and Microsoft calendarization.
C49: EV / TTM sales | D49: =D16/D23 -> 9.0663018 | E49: =E16/E23 -> 11.730705 | F49: =F16/F23 -> 7.8739469 | G49: =G16/G23 -> 3.4872447
C50: EV / EBITD | D50: =D16/D45 -> 23.384466 | E50: =E16/E45 -> 20.537971 | F50: =F16/F45 -> 16.567764 | G50: =G16/G45 -> 18.856253
C53: Peer valuation spread | D53: Low | E53: Median | F53: High | J53: MSFT, META, AMZN only. GOOGL excluded from peer median.
C54: P/E | D54: =MIN(E47:G47) -> 19.927041 | E54: =MEDIAN(E47:G47) -> 26.488307 | F54: =MAX(E47:G47) -> 29.377822
C55: EV/Sales | D55: =MIN(E49:G49) -> 3.4872447 | E55: =MEDIAN(E49:G49) -> 7.8739469 | F55: =MAX(E49:G49) -> 11.730705
C56: EV/EBITD | D56: =MIN(E50:G50) -> 16.567764 | E56: =MEDIAN(E50:G50) -> 18.856253 | F56: =MAX(E50:G50) -> 20.537971
C57: Forward P/E (CY2027 adjusted) | D57: =MIN(E48:G48) -> 20.482818 | E57: =MEDIAN(E48:G48) -> 23.923445 | F57: =MAX(E48:G48) -> 24.324138
C59: P/E implied common value / share | D59: =D54*$D$33/$D$9 -> 397.75709 | E59: =E54*$D$33/$D$9 -> 528.72438 | F59: =F54*$D$33/$D$9 -> 586.40103
C60: EV/Sales implied value / share | D60: =(D55*$D$23+DCF!$D$48)/$D$9 -> 133.90718 | E60: =(E55*$D$23+DCF!$D$48)/$D$9 -> 293.83207 | F60: =(F55*$D$23+DCF!$D$48)/$D$9 -> 434.43691
C61: EV/EBITD implied value / share | D61: =(D56*$D$45+DCF!$D$48)/$D$9 -> 240.95074 | E61: =(E56*$D$45+DCF!$D$48)/$D$9 -> 273.29739 | F61: =(F56*$D$45+DCF!$D$48)/$D$9 -> 297.06765
C62: Forward P/E implied value / share | D62: =D57*$D$77 -> 312.36298 | E62: =E57*$D$77 -> 364.83254 | F62: =F57*$D$77 -> 370.9431
C64: GAAP P/E includes investment gains. EBITD adds only PPE depreciation for all issuers. Forward P/E uses adjusted consensus. Do not blend methods.
C66: EV excludes leases for all. EBITD retains intangible amortization expense; no SBC, content, operating-lease or other cash-flow addbacks.
C72: Forward earnings inputs | D72: GOOGL | E72: MSFT | F72: META | G72: AMZN | J72: F1–F4: S&P Global adjusted non-GAAP EPS via Stock Analysis; updated 2026-10-16.
C73: FY2027 adjusted EPS | D73: 15.25 | E73: 19.78 | F73: 34.63 | G73: 10.45
C74: FY2027 period end | D74: 46752 | E74: 46568 | F74: 46752 | G74: 46752
C75: FY2028 adjusted EPS (MSFT) | E75: 23.72
C76: CY2027 weight from FY2027 | D76: 1 | E76: 0.5 | F76: 1 | G76: 1
C77: CY2027 adjusted EPS | D77: =D73 -> 15.25 | E77: =E73*E76+E75*(1-E76) -> 21.75 | F77: =F73 -> 34.63 | G77: =G73 -> 10.45
C78: Consensus updated | D78: 46311 | E78: 46311 | F78: 46311 | G78: 46311
C80: MSFT CY2027 EPS = 50% FY2027 + 50% FY2028. Equal-half approximation; not a quarterly consensus forecast.
C82: Adjusted consensus EPS is distinct from historical GAAP earnings. Provider adjustments are retained; the DCF still expenses SBC.
C84: TTM bridge: Jul 2025–Jun 2026 | D84: GOOGL | E84: MSFT | F84: META | G84: AMZN | J84: X1–X4: reported PP&E depreciation. Calendar issuers: FY2025 - H1 2025 + H1 2026. MSFT FY2026 matches TTM.
C85: TTM EBIT | D85: =D28 -> 147628 | E85: =E28 -> 155237 | F85: =F28 -> 86926 | G85: =G28 -> 93712
C86: TTM PPE depreciation | D86: =D38 -> 25237 | E86: =E38 -> 34300 | F86: =F38 -> 21550 | G86: =G38 -> 49741
C87: TTM EBITD = EBIT + PPE dep. | D87: =D85+D86 -> 172865 | E87: =E85+E86 -> 189537 | F87: =F85+F86 -> 108476 | G87: =G85+G86 -> 143453
C88: EV / EBITD | D88: =D16/D87 -> 23.384466 | E88: =E16/E87 -> 20.537971 | F88: =F16/F87 -> 16.567764 | G88: =G16/G87 -> 18.856253
C89: Headline reconciliation difference | D89: =D45-D87 -> 0 | E89: =E45-E87 -> 0 | F89: =F45-F87 -> 0 | G89: =G45-G87 -> 0
C91: EBITD is deliberate: EBIT + PPE depreciation only. Intangible amortization stays expensed for every issuer; no estimates are introduced.
C93: No SBC, content, operating-lease asset or other cash-flow addbacks. EV excludes lease liabilities uniformly; lease mixes still differ.
C95: Full TTM intangible amortization is not verified for GOOGL / AMZN. EBITD replaces EBITDA by the presenter’s choice; it is not EBITDA.
